Workbook
Name _MWM_WSO_DATA: '_What Stands Out Dropdowns v3'!$B$2:$Q$267
Name _MWM_WSO_KEYS: '_What Stands Out Dropdowns v3'!$A$2:$A$267

Sheet Business Intake
A1: Business Name | B1: City | C1: State | D1: Original Category | E1: Main Category | F1: Subcategory | G1: Website or Social Media | H1: Brief Description (1–2 sentences) | I1: Vibe 1 | J1: Vibe 2 | K1: Vibe 3 | L1: Ownership 1 | M1: Ownership 2 | N1: Recommended By | O1: Notes | P1: Address | Q1: Zip Code | R1: Quick Review Preview 1 | S1: Quick Review Preview 2 | T1: Quick Review Preview 3 | U1: Verification Status
A2: The Nail Jawns | B2: Philadelphia | C2: PA | D2: Nail Salon | E2: Beauty & Personal Care | F2: Nail Salons & Nail Artists | G2: https://www.tiktok.com/@the.nail.jawns | I2: Soft Life | J2: Luxury Without The Attitude | K2: Main Character Energy | L2: Black / African American-Owned | N2: Friend | O2: Walk-ins Welcomed, Appointments preferred. | P2: 429 N. 64th St | Q2: 19151 | R2: Style Lasted | S2: Book Now | T2: Worth The Price
A3: Cherished Beauty Supply | B3: Darby | C3: PA | D3: Beauty | E3: Beauty & Personal Care | F3: Beauty Supply | G3: https://www.tiktok.com/@cherishedbeautysupply | H3: Plant-Based Hair & Skin Care. Black-Owned Beauty Supply | I3: Chill & Restore | J3: For The Culture | L3: Black / African American-Owned | N3: Friend | O3: Willing to Ship! | P3: 526 Main St | Q3: 19023 | R3: Worth The Price
A4: Angie's Eats | B4: Philadelphia | C4: PA | D4: Restaurant | E4: Food & Drink | F4: Restaurants | G4: https://www.tiktok.com/@angieslne | H4: Latin Soul Food | I4: Locals Know | J4: Take Somebody From Out of Town | L4: Latino / Hispanic-Owned | N4: Personal visit | O4: The Shrimp Alfredo with 6 wings combo is FIRE | R4: Portions With Love | S4: Seasoned Right | T4: I Sent The Group Chat
A5: ISSAAESTHETICS Beauty Salon & Barbershop | B5: Silver Spring | C5: MD | D5: Barber/Salon | E5: Beauty & Personal Care | F5: Hair Salons | G5: https://www.instagram.com/issaaestheticsbeauty | H5: Laser Hair Removal/Blow Outs/Chemical Peels and More | I5: Neighborhood Love | L5: Dominican-Owned | N5: Friend | O5: Se Habla Espanol | P5: 11409 Amherst Ave Unit A | Q5: 20902 | R5: On Time, Every Time | S5: Worth The Price
A6: Candy Clouds By Cass | B6: Santa Clara | C6: CA | D6: Restaurant | E6: Food & Drink | F6: Desserts & Sweets | G6: https://www.instagram.com/candycloudsbycass | H6: Sweet Clouds for Every Celebration! | I6: Bougie Treat | L6: Minority-Owned (general / legacy) | O6: Serving the Bay Area | R6: Sweet, Not Too Sweet | S6: Don't Sleep On This One
A7: Little Essentials | B7: New York | C7: NY | E7: Community & Nonprofit | F7: Youth Organizations | G7: https://www.littleessentials.org | H7: Little Essentials offers at-risk families living in poverty urgently needed children’s supplies and parenting education to promote the health, well-being, and safety of their children ages 0-5. Little Essentials offers at-risk families living in poverty urgently needed children’s supplies and parenting education to promote the health, well-being, and safety of their children ages 0-5. | I7: Neighborhood Love | L7: Minority-Owned (general / legacy) | O7: 80, 265 NYC Children Served 37, 628 NYC Families Helped 1, 809, 338 Diapers Distributed | P7: 63 Flushing Avenue, Bldg 131, Ste 205 | Q7: 11205 | R7: Help Was Real | S7: No Judgment
A8: Philly Barber Studios | B8: Philadelphia | C8: PA | E8: Beauty & Personal Care | F8: Barbershops | G8: https://www.instagram.com/phillybarberstudios/ | H8: From precision fade haircuts to straight razor shaving. Cutting, trimming your head to Perfection. Shampoo and conditioner, then hot towel and neck shave. | I8: Neighborhood Love | J8: For The Culture | L8: Minority-Owned (general / legacy) | O8: Good for kids, book appointment | P8: 7938 Oxford Ave | Q8: 19111 | R8: Patient With Kids | S8: Sharpest Lineup | T8: Patient With Kids
A9: AMINA | B9: Philadelphia | C9: PA | E9: Food & Drink | F9: Restaurants | G9: https://www.aminaphilly.com | H9: Amina Restaurant is a restaurant and bar in No Libs Philadelphia, serving up American Southern cuisine. Owner Felicia Wilson and Chef Partner Darryl Harmon are innovators in the Southern cuisine space. | I9: Date Night | J9: Locals Know | K9: Take Somebody From Out of Town | L9: Black / African American-Owned | M9: Woman-Owned | N9: Personal visit | O9: Saturday Brunch books Fast so make a reservation | P9: 1102 Germantown Ave | Q9: 19123 | R9: Cooks Like Home | S9: Seasoned Right | T9: Grandma Approved
A10: SOUTH | B10: Philadelphia | C10: PA | E10: Food & Drink | F10: Restaurants | G10: https://www.southjazzkitchen.com | H10: Since 2015, SOUTH has served up elevated comfort food rooted in the food of the south.At SOUTH, America’s original music meets southern heritage cuisine in Philadelphia’s Spring Garden neighborhood on Avenue of the Arts North. | I10: Date Night | J10: Late Night Vibes | K10: Locals Know | L10: Black / African American-Owned | N10: Personal visit | O10: Dressy and business casual attire are preferred. | P10: 600 N Broad St | Q10: 19130 | R10: Book This Table | S10: Don't Sleep On This One

Sheet Category Reference
A1: Main Category | B1: Subcategory | C1: Notes
A2: Food & Drink | B2: Restaurants | C2: Approved source-of-truth taxonomy
A3: Food & Drink | B3: Cafés & Coffee | C3: Approved source-of-truth taxonomy
A4: Food & Drink | B4: Bakeries | C4: Approved source-of-truth taxonomy
A5: Food & Drink | B5: Desserts & Sweets | C5: Approved source-of-truth taxonomy
A6: Food & Drink | B6: Food Trucks & Mobile Food | C6: Approved source-of-truth taxonomy
A7: Food & Drink | B7: Catering | C7: Approved source-of-truth taxonomy
A8: Food & Drink | B8: Bars & Lounges | C8: Approved source-of-truth taxonomy
A9: Food & Drink | B9: Juice & Smoothies | C9: Approved source-of-truth taxonomy
A10: Food & Drink | B10: Specialty Foods | C10: Approved source-of-truth taxonomy
A11: Food & Drink | B11: Meal Prep | C11: Approved source-of-truth taxonomy
A12: Food & Drink | B12: Grocery & Markets | C12: Approved source-of-truth taxonomy
... A286: Home & Property Services | B286: Mortgage & Homebuyer Counseling | C286: ADDED v2 — specialty/professional discovery gap

Sheet Vibe Reference
A1: Main Category | B1: Vibe Label | C1: Meaning / Helper Text | D1: Source | E1: Replit Rule
A2: Food & Drink | B2: Date Night | C2: Worth getting cute for | D2: Existing specification | E2: Show only when category/subcategory is vibe-eligible
A3: Food & Drink | B3: Hood Classic | C3: Been here forever, still hits | D3: Existing specification | E3: Show only when category/subcategory is vibe-eligible
A4: Food & Drink | B4: Bougie Treat | C4: Payday / splurge spot | D4: Existing specification | E4: Show only when category/subcategory is vibe-eligible
A5: Food & Drink | B5: Family Reunion Energy | C5: Loud, warm, everybody's welcome | D5: Existing specification | E5: Show only when category/subcategory is vibe-eligible
A6: Food & Drink | B6: Sunday Best | C6: After-church energy | D6: Existing specification | E6: Show only when category/subcategory is vibe-eligible
A7: Food & Drink | B7: Late Night Vibes | C7: Open when you need it | D7: Existing specification | E7: Show only when category/subcategory is vibe-eligible
A8: Food & Drink | B8: Turn Up | C8: Music up, energy high | D8: Existing specification | E8: Show only when category/subcategory is vibe-eligible
A9: Food & Drink | B9: Cookout Approved | C9: Passes the family test | D9: Existing specification | E9: Show only when category/subcategory is vibe-eligible
A10: Food & Drink | B10: Like Home | C10: Familiar, comfortable, somebody's-kitchen energy | D10: Added | E10: Show only when category/subcategory is vibe-eligible
A11: Food & Drink | B11: Auntie Energy | C11: Warm service; somebody is making sure you're good | D11: Added | E11: Show only when category/subcategory is vibe-eligible
A12: Food & Drink | B12: Tía Energy | C12: Warm, familiar, lovingly involved | D12: Added | E12: Show only when category/subcategory is vibe-eligible
... A132: Other Services | B132: N/A — Use Endorsements, Not Vibes | C132: This category should rely on earned endorsements instead of atmosphere labels. | D132: System rule | E132: Do not render The Vibe by default

Sheet Ownership Reference
A1: Ownership Designation | B1: Use | C1: Rule
A2: Black / African American-Owned | B2: Selectable as Ownership 1 or Ownership 2 | C2: Self-identified / documented only; never infer from name, photo, location, or cuisine
A3: African-Owned | B3: Selectable as Ownership 1 or Ownership 2 | C3: Self-identified / documented only; never infer from name, photo, location, or cuisine
A4: West African-Owned | B4: Selectable as Ownership 1 or Ownership 2 | C4: Self-identified / documented only; never infer from name, photo, location, or cuisine
A5: Nigerian-Owned | B5: Selectable as Ownership 1 or Ownership 2 | C5: Self-identified / documented only; never infer from name, photo, location, or cuisine
A6: Ghanaian-Owned | B6: Selectable as Ownership 1 or Ownership 2 | C6: Self-identified / documented only; never infer from name, photo, location, or cuisine
A7: Liberian-Owned | B7: Selectable as Ownership 1 or Ownership 2 | C7: Self-identified / documented only; never infer from name, photo, location, or cuisine
A8: Sierra Leonean-Owned | B8: Selectable as Ownership 1 or Ownership 2 | C8: Self-identified / documented only; never infer from name, photo, location, or cuisine
A9: Senegalese-Owned | B9: Selectable as Ownership 1 or Ownership 2 | C9: Self-identified / documented only; never infer from name, photo, location, or cuisine
A10: Guinean-Owned | B10: Selectable as Ownership 1 or Ownership 2 | C10: Self-identified / documented only; never infer from name, photo, location, or cuisine
A11: Gambian-Owned | B11: Selectable as Ownership 1 or Ownership 2 | C11: Self-identified / documented only; never infer from name, photo, location, or cuisine
A12: Ivorian-Owned | B12: Selectable as Ownership 1 or Ownership 2 | C12: Self-identified / documented only; never infer from name, photo, location, or cuisine
... A91: Minority-Owned (general / legacy) | B91: Selectable as Ownership 1 or Ownership 2 | C91: Self-identified / documented only; never infer from name, photo, location, or cuisine

Sheet Quick Reviews
A1: Main Category | B1: Endorsement / Quick Review | C1: Type | D1: Subcategory Scope | E1: Helper Text | F1: Source
A2: Food & Drink | B2: Worth The Drive | C2: universal | D2: all | E2: You'd cross town for this | F2: Existing specification
A3: Food & Drink | B3: Portions With Love | C3: universal | D3: all | E3: They didn't skimp | F3: Existing specification
A4: Food & Drink | B4: Clean & Cared For | C4: universal | D4: all | E4: The space is kept right | F4: Existing specification
A5: Food & Drink | B5: Grandma Approved | C5: adaptive | D5: all | E5: She would approve of this food | F5: Existing specification
A6: Food & Drink | B6: Cooks Like Home | C6: adaptive | D6: Restaurants; Catering; Private Chefs; Meal Prep; Specialty Foods | E6: Tastes like somebody's kitchen | F6: Existing specification
A7: Food & Drink | B7: They Speak My Language | C7: adaptive | D7: all | E7: You can order comfortably | F7: Existing specification
A8: Food & Drink | B8: Seasoned Right | C8: specific | D8: Restaurants; Food Trucks & Mobile Food; Catering; Meal Prep; Private Chefs | E8: No bland plates here | F8: Existing specification
A9: Food & Drink | B9: Plate Came Correct | C9: specific | D9: Restaurants; Food Trucks & Mobile Food | E9: Looked and tasted like the picture | F9: Existing specification
A10: Food & Drink | B10: They Don't Rush The Recipe | C10: specific | D10: Restaurants; Bakeries; Specialty Foods | E10: Slow-cooked, done properly | F10: Existing specification
A11: Food & Drink | B11: Ask For The Special | C11: specific | D11: Restaurants; Food Trucks & Mobile Food; Bars & Lounges | E11: The off-menu move is the move | F11: Existing specification
A12: Food & Drink | B12: Recipe From The Motherland | C12: specific | D12: Restaurants; Bakeries; Specialty Foods; Grocery & Markets | E12: Traditional, not watered down | F12: Existing specification
... A336: Other Services | B336: Save Their Number | C336: recommendation | D336: all | E336: A provider worth keeping | F336: Added

Sheet Replit Source of Truth
A1: Mapping With Melanin™ — Permanent Business Taxonomy + Endorsement Source of Truth
A3: System | B3: Authoritative workbook tab
A4: Business taxonomy | B4: Category Reference
A5: Vibes | B5: Vibe Reference
A6: Ownership designations | B6: Ownership Reference
A7: One-tap endorsements | B7: Quick Reviews
A8: Entry/import model | B8: Business Intake
A9: Maximum ownership designations | B9: 2
A10: Negative public endorsements | B10: Never — route concerns to private feedback/report flow
A12: PASTE THIS INTO REPLIT
A13: PERMANENT SOURCE-OF-TRUTH REQUIREMENT — IMPORT AND PRESERVE Use the attached Mapping With Melanin™ MASTER Business Directory workbook as the authoritative taxonomy for business ingestion. DO NOT rely on Agent chat memory. 1. Import and preserve the exact Main Category → Subcategory relationships from the "Category Reference" sheet. 2. Import the exact Vibe labels, helper text, eligibility and source status from "Vibe Reference". 3. Import the ownership designations from "Ownership Reference". A listing may have up to TWO ownership designations. Ownership is self-identified/documented only. Never infer race, ethnicity, nationality, gender, LGBTQIA+ status, disability, veteran status, or immigration background from a name, image, neighborhood, cuisine, language, or model prediction. 4. Import the complete one-tap endorsement vocabulary from "Quick Reviews". Preserve the wording. Do not rewrite, sanitize, professionalize, merge, or replace culturally specific wording. 5. Endorsements are praise-only. Concerns and negative experiences route to the existing private feedback / safety report flow. 6. Candidate endorsements are driven by business category + subcategory. User identity must never determine which businesses or endorsement families are eligible. 7. Culturally adaptive labels may render according to the user's explicitly selected community-language preference, but all variants for the same tag family roll up to ONE underlying count. Never infer the preference. 8. Keep Vibes separate from endorsements. Vibes describe atmosphere/visit type; endorsements describe what the community praises about the business. 9. Business owners may not award themselves endorsements or earned recognition badges. 10. Store these files in version control and treat them as permanent product specifications: docs/product/business-taxonomy.md docs/product/vibe-taxonomy.md docs/product/ownership-designations.md docs/product/endorsement-system.md data/business_categories.json data/vibe_tags.json data/ownership_designations.json data/endorsement_tags_seed.json data/endorsement_tag_variants_seed.json BEFORE WRITING OR MIGRATING DATA: - Perform a read-only comparison of the current database/code values against this workbook. - Report every conflict, missing category, orphaned subcategory, duplicate tag, renamed tag, and unsupported ownership designation. - Do not delete or overwrite existing production data until founder approval. - Preserve original submitted category values for audit/traceability while mapping them to the standardized category/subcategory. - Confirm the import counts back to me before implementation.
A40: V2 — THE REAL PROFESSIONAL TRUST LAYER
A41: THE REAL is the permanent user-facing name for the professional trust layer. Do not rename it. Do not treat it as a Vibe. A profile gets THE REAL OR The Vibe, never both. "What stands out?" endorsements remain universal. Import the complete source-derived THE REAL rows from the "THE REAL Reference" sheet. Preserve migrated keys and historical counts in production. Rows marked ADDED v2 are deliberate proposed expansions and must remain distinguishable during the read-only audit. Professional/service categories using THE REAL: Legal & Government Services; Professional Services; Financial & Business Services; Home & Property Services; Automotive & Transportation; Technology & Digital Services; Pets & Animal Services; Other Services. Health & Wellness is subcategory-routed: clinical/care gets THE REAL; Fitness & Gyms, Personal Trainers, and Yoga & Pilates get The Vibe. Candidate tags are determined by category + subcategory only. Never infer a user's race, ethnicity, gender, immigration status, religion, disability, or other identity to decide what to show. Cultural-language variants may use an explicitly saved preference only. Before implementation: READ-ONLY audit current code/database against this workbook. Report missing categories/subcategories, misclassified tags, duplicate/renamed tags, orphaned historical counts, any THE REAL/The Vibe co-rendering, and any identity-inference logic. Do not delete/reinsert migrated tags and do not implement until founder approval.

Sheet _Subcategory Lists
A1: Food & Drink | B1: Beauty & Personal Care | C1: Health & Wellness | D1: Shopping & Retail | E1: Travel & Hospitality | F1: Arts, Culture & Entertainment | G1: Professional Services | H1: Home & Property Services | I1: Automotive & Transportation | J1: Events & Celebrations | K1: Education & Learning | L1: Children & Family | M1: Community & Nonprofit | N1: Faith & Spirituality | O1: Media & Creative Services | P1: Sports & Recreation | Q1: Pets & Animal Services | R1: Technology & Digital Services | S1: Financial & Business Services | T1: Legal & Government Services | U1: Agriculture & Specialty Producers | V1: Other Services
A2: Restaurants | B2: Hair Salons | C2: Primary Care & Medical Practices | D2: Clothing & Fashion | E2: Hotels & Resorts | F2: Museums | G2: Accounting & Tax | H2: Real Estate Agents & Brokers | I2: Auto Repair | J2: Event Planning | K2: Childcare & Daycare | L2: Childcare | M2: Nonprofits | N2: Churches | O2: Content Creators | P2: Sports Clubs | Q2: Veterinarians | R2: Software Companies | S2: Banks & Credit Unions | T2: Attorneys & Law Firms | U2: Farms | V2: Laundry & Dry Cleaning
A3: Cafés & Coffee | B3: Barbershops | C3: Dental | D3: Shoes & Accessories | E3: Bed & Breakfasts | F3: Galleries | G3: Legal Services | H3: Property Management | I3: Auto Detailing | J3: Wedding Planning | K3: Preschools | L3: Children's Activities | M3: Community Organizations | N3: Mosques | O3: Influencers / Cultural Ambassadors | P3: Recreational Centers | Q3: Pet Grooming | R3: App Developers | S3: Financial Advisors | T3: Mediation | U3: Farmers Markets | V3: Tailoring & Alterations
A4: Bakeries | B4: Braiders & Natural Hair | C4: Mental Wellness & Therapy | D4: Jewelry | E4: Vacation Rentals | F4: Cultural Centers | G4: Insurance | H4: Contractors | I4: Car Wash | J4: Event Venues | K4: Tutoring | L4: Indoor Play | M4: Foundations | N4: Synagogues | O4: Podcasts | P4: Coaches & Training | Q4: Pet Boarding | R4: Web Developers | S4: Bookkeeping | T4: Notary Services | U4: Urban Farms | V4: Shoe Repair
A5: Desserts & Sweets | B5: Nail Salons & Nail Artists | C5: Physical Therapy | D5: Gifts | E5: Travel Agencies & Advisors | F5: Performing Arts | G5: Financial Services | H5: Construction | I5: Tire Services | J5: Party Rentals | K5: Test Preparation | L5: Camps | M5: Mutual Aid | N5: Temples | O5: Radio | P5: Youth Sports | Q5: Dog Walking & Pet Sitting | R5: IT Support | S5: Tax Preparation | T5: Immigration Services | U5: Specialty Growers | V5: Locksmiths
A6: Food Trucks & Mobile Food | B6: Makeup Artists | C6: Chiropractic | D6: Home Décor | E6: Tour Operators | F6: Theaters | G6: Business Consulting | H6: Electricians | I6: Auto Dealers | J6: Decorators | K6: Colleges & Universities | L6: Family Entertainment | M6: Advocacy Organizations | N6: Spiritual Centers | O6: Publications & Magazines | P6: Golf | Q6: Pet Training | R6: Cybersecurity | S6: Lending & Financing | T6: Legal Document Services | U6: Floriculture | V6: Shipping & Mailing
A7: Catering | B7: Estheticians & Skincare | C7: Nutrition & Dietitians | D7: Furniture | E7: Tour Guides | F7: Music & Live Entertainment | G7: Marketing & Advertising | H7: Plumbing | I7: Auto Body & Collision | J7: Florists | K7: HBCUs | L7: Parenting Services | M7: Youth Organizations | N7: Faith-Based Organizations | O7: Writers & Authors | P7: Swimming | Q7: Pet Daycare | R7: AI & Automation | S7: Mortgage Services | T7: Government Offices | U7: Food Producers | V7: Storage
A8: Bars & Lounges | B8: Spas | C8: Fitness & Gyms | D8: Books & Bookstores | E8: Transportation Services | F8: DJs | G8: Public Relations | H8: HVAC | I8: Towing & Roadside Assistance | J8: Balloon Artists | K8: Trade & Vocational Schools | L8: Children's Parties | M8: Senior Services | N8: Religious Bookstores & Retail | O8: Photography | P8: Martial Arts | Q8: Pet Stores & Supplies | R8: SaaS | S8: Credit Services | T8: Public Services | U8: Beverage Producers | V8: Funeral & Memorial Services
A9: Juice & Smoothies | B9: Massage | C9: Personal Trainers | D9: Art & Collectibles | E9: Luggage & Travel Products | F9: Entertainment Venues | G9: Graphic Design & Branding | H9: Landscaping & Lawn Care | I9: Car Rental | J9: DJs & Entertainment | K9: Professional Training | L9: Youth Programs | M9: Community Centers | N9: Faith-Based Community Services | O9: Videography | P9: Dance & Movement | R9: Digital Products | S9: Business Funding | U9: Agricultural Products | V9: Personal Concierge
A10: Specialty Foods | B10: Lashes & Brows | C10: Yoga & Pilates | D10: Specialty Retail | E10: Travel Experiences | F10: Nightlife | G10: Web & App Development | H10: Cleaning Services | I10: Chauffeur & Private Driver | J10: Photographers | K10: Music Lessons | L10: Children's Retail | M10: Cultural Organizations | O10: Production Companies | P10: Outdoor Recreation | R10: Technology Consulting | S10: Investment Services | V10: Other
A11: Meal Prep | B11: Beauty Supply | C11: Wellness Centers | D11: Children's Retail | F11: Festivals | G11: IT & Technology Services | H11: Interior Design | I11: Transportation Companies | J11: Videographers | K11: Dance Schools | L11: Maternity & Baby Services | M11: Professional Associations | O11: Recording Studios | P11: Adventure Experiences
A12: Grocery & Markets | B12: Cosmetics & Beauty Brands | C12: Doula & Birth Services | D12: Pet Products | F12: Attractions | G12: Printing | H12: Moving Services | J12: Caterers | K12: Art Classes | M12: Chambers & Business Organizations | O12: Music Production
A13: Private Chefs | B13: Mobile Beauty Services | C13: Holistic Wellness | D13: Online Shops | F13: Gaming & Recreation | G13: Translation & Language Services | H13: Handyman Services | J13: Cakes & Desserts | K13: Language Instruction | O13: Creative Studios
C14: Pharmacies | F14: Photography | G14: Staffing & Recruiting | H14: Home Inspection | J14: Invitations & Stationery | K14: Educational Programs
C15: Home Health & Caregiving | F15: Videography | G15: Virtual Assistants | H15: Roofing | J15: Photo Booths
H16: Pest Control

Sheet _Vibe Lists
A1: Food & Drink | B1: Beauty & Personal Care | C1: Health & Wellness | D1: Shopping & Retail | E1: Travel & Hospitality | F1: Arts, Culture & Entertainment | G1: Professional Services | H1: Home & Property Services | I1: Automotive & Transportation | J1: Events & Celebrations | K1: Education & Learning | L1: Children & Family | M1: Community & Nonprofit | N1: Faith & Spirituality | O1: Media & Creative Services | P1: Sports & Recreation | Q1: Pets & Animal Services | R1: Technology & Digital Services | S1: Financial & Business Services | T1: Legal & Government Services | U1: Agriculture & Specialty Producers | V1: Other Services
A2: Date Night | B2: Soft Life | C2: Chill & Restore | D2: Hood Classic | E2: Romantic Escape | F2: Date Night | G2: N/A — Use Endorsements, Not Vibes | H2: N/A — Use Endorsements, Not Vibes | I2: N/A — Use Endorsements, Not Vibes | J2: Family Reunion Energy | K2: Teach The Kids | L2: Kid Chaos Friendly | M2: Neighborhood Love | N2: Sunday Best | O2: Creative Scene | P2: Turn Up | Q2: N/A — Use Endorsements, Not Vibes | R2: N/A — Use Endorsements, Not Vibes | S2: N/A — Use Endorsements, Not Vibes | T2: N/A — Use Endorsements, Not Vibes | U2: Grand Rising | V2: N/A — Use Endorsements, Not Vibes
A3: Hood Classic | B3: Auntie Energy | C3: Peaceful Energy | D3: Locals Know | E3: Family Reunion Energy | F3: Turn Up | J3: Sunday Best | K3: Come As You Are | L3: Family Reunion Energy | M3: For The Culture | N3: Come As You Are | O3: Chill & Create | P3: Family Reunion Energy | U3: Family Reunion Energy
A4: Bougie Treat | B4: Tía Energy | C4: Come As You Are | D4: Hidden Gem | E4: Solo Traveler Comfortable | F4: Grown & Sexy | J4: Turn Up | K4: Creative Energy | L4: Rainy Day Rescue | M4: Come As You Are | N4: Quiet & Prayerful | O4: Main Character Energy | P4: Chill & Move | U4: Chill & Create
A5: Family Reunion Energy | B5: Main Character Energy | C5: Auntie Energy | D5: Bougie Treat | E5: Bougie Treat | F5: Hood Classic | J5: Grown & Sexy | K5: Community Classroom | L5: Toddler Safe | M5: Everybody Knows Somebody | N5: Praise Break Energy | O5: For The Culture | P5: Early Bird Energy | U5: Bring The Cousins
A6: Sunday Best | B6: Sunday Best | C6: Family Care | D6: Chill & Create | E6: Chill & Restore | F6: Chill & Create | J6: Bougie Treat | L6: Big Kid Approved | M6: Family Reunion Energy | N6: Family Worship | O6: Grown & Sexy | P6: Kid Chaos Friendly | U6: Hood Classic
A7: Late Night Vibes | B7: Chill & Restore | C7: Wellness Reset | D7: Bring The Cousins | E7: Girls Trip Ready | F7: Late Night Vibes | J7: Kid Chaos Friendly | L7: Parents Can Breathe | M7: History Lives Here | N7: Young Adult Friendly | P7: Adventure Ready | U7: Cookout Approved
A8: Turn Up | B8: Come As You Are | D8: For The Culture | E8: Grand Rising | F8: Family Reunion Energy | J8: Late Night Vibes | L8: Birthday Party Ready | N8: Auntie Energy | P8: Bring The Cousins | U8: Locals Know
A9: Cookout Approved | B9: For The Culture | D9: Take Somebody From Out of Town | E9: Bring The Cousins | F9: Sunday Best | J9: Cookout Approved | L9: Bring The Cousins | N9: Everybody Knows Somebody | U9: Teach The Kids
A10: Like Home | B10: Neighborhood Love | E10: Passport Energy | F10: History Lives Here | J10: Made For Memories | L10: Teach The Kids
A11: Auntie Energy | B11: Luxury Without The Attitude | E11: Take Somebody From Out of Town | F11: Culture On The Walls | J11: Bring The Cousins | L11: Like Home
A12: Tía Energy | E12: Luxury Without The Attitude | F12: Teach The Kids | J12: Luxury Without The Attitude
A13: Abuela Approved Energy | E13: Locals Know | F13: Creative Scene
A14: Soft Life
A15: Take Somebody From Out of Town
A16: Locals Know
A17: Passport Energy

Sheet _Quick Review Matrix
A1: Food & Drink | B1: Beauty & Personal Care | C1: Health & Wellness | D1: Shopping & Retail | E1: Travel & Hospitality | F1: Arts, Culture & Entertainment | G1: Professional Services | H1: Home & Property Services | I1: Automotive & Transportation | J1: Events & Celebrations | K1: Education & Learning | L1: Children & Family | M1: Community & Nonprofit | N1: Faith & Spirituality | O1: Media & Creative Services | P1: Sports & Recreation | Q1: Pets & Animal Services | R1: Technology & Digital Services | S1: Financial & Business Services | T1: Legal & Government Services | U1: Agriculture & Specialty Producers | V1: Other Services
A2: Worth The Drive | B2: On Time, Every Time | C2: Didn't Rush Me | D2: Quality Held Up | E2: Exactly As Pictured | F2: Worth The Ticket | G2: Straight With Me | H2: Showed Up When They Said | I2: Fair Price | J2: Delivered Exactly What I Asked | K2: My Child Improved | L2: Clean & Safe | M2: Help Was Real | N2: All Are Welcome (And Mean It) | O2: Delivered On Deadline | P2: Well Kept Facility | Q2: Gentle Hands | R2: Delivered What Was Promised | S2: Straight With Me | T2: Answered The Phone | U2: Fresh & Honest | V2: Fast & Reliable
A3: Portions With Love | B3: Clean Station | C3: Took Time To Explain | D3: Fair Prices | E3: Spotless | F3: Staff Was Welcoming | G3: Delivered On Time | H3: Cleaned Up After | I3: Fast Turnaround | J3: On Time Setup | K3: Teachers Actually Care | L3: Staff Was Patient | M3: No Judgment | N3: Visitors Feel At Home | O3: Easy To Work With | P3: Coaches Show Up | Q3: Fair Price | R3: Responsive | S3: No Hidden Fees | T3: Clear About Cost | U3: Fair Prices | V3: Fair Price
A4: Clean & Cared For | B4: Worth The Price | C4: Made Me Feel Heard | D4: No Follow-Around | E4: Worth The Stay | F4: Bring A Friend | G4: Answered The Phone | H4: Quote Matched The Bill | I4: Explained The Repair | J4: Worth Every Dollar | K4: Communication Was Clear | L4: Fair Price For Families | M4: Answered When I Called | N4: No Pressure, Just Peace | O4: Worth The Investment | P4: Fair Fees | Q4: Clean Facility | R4: Fair Scope & Price | S4: Answered The Phone | T4: On Time & Prepared | U4: Friendly Growers | V4: Careful With My Things
A5: Grandma Approved | B5: Blessed Hands | C5: Treated Me Like Family | D5: Grandma Approved | E5: Treated Me Like Family | F5: For The Culture | G5: Treated Me Like Family | H5: Treated Me Like Family | I5: Unc Trusts This Shop | J5: Sunday Best Ready | K5: Grandma Approved | L5: Grandma Approved | M5: Treated Me Like Family | N5: Mothers Of The Church Approve | O5: For The Culture | P5: For The Culture | Q5: Treated Me Like Family | R5: For The Culture | S5: Grandma Trusts Them | T5: They Speak My Language | U5: Grandma Approved | V5: Treated Me Like Family
A6: Cooks Like Home | B6: They Know Our Hair | C6: They Speak My Language | D6: For The Culture | E6: They Speak My Language | F6: Grandma Approved | G6: They Speak My Language | H6: Grandma Approved | I6: Treated Me Like Family | J6: Treated Me Like Family | K6: For The Culture | L6: For The Culture | M6: For The Culture | N6: They Speak My Language | O6: Blessed Hands | P6: Grandma Approved | Q6: Blessed Hands | R6: Treated Me Like Family | S6: Treated Me Like Family | T6: Treated Me Like Family | U6: Grows What We Cook | V6: Grandma Approved
A7: They Speak My Language | B7: Grandma Approved | C7: Grandma Trusts Them | D7: Treated Me Like Family | E7: For The Culture | F7: Sunday Best Ready | G7: For The Culture | H7: They Speak My Language | I7: They Speak My Language | J7: For The Culture | K7: They Speak My Language | L7: They Get Our Hair | M7: Elders Are Honored | N7: For The Culture | O7: Treated Me Like Family | P7: Treated Me Like Family | Q7: They Speak My Language | R7: They Speak My Language | S7: They Speak My Language | T7: For The Culture | U7: For The Culture | V7: Blessed Hands
A8: Seasoned Right | B8: Sharpest Lineup | C8: This Doctor Listens | D8: Found My Size | E8: Felt Safe The Whole Time | F8: Our Story Told Right | G8: Explained It Plain | H8: Didn't Talk Down To Me | I8: Didn't Upsell Me | J8: Handled My Whole Day | K8: My Kids See Themselves | L8: My Kids See Themselves | M8: Showed Up For The Block | N8: The Spirit Lives Here | O8: Told My Story Right | P8: Coach Builds Character | Q8: My Dog Wasn't Scared | R8: Explained It Without The Jargon | S8: Said Yes When Others Said No | T8: Fought For Me | U8: Picked This Morning | V8: Nothing Lost, Nothing Damaged
A9: Plate Came Correct | B9: Braids Didn't Hurt | C9: Believed My Pain | D9: Found My Shade | E9: Host Checked On Me | F9: DJ Read The Room | G9: No Surprise Fees | H9: Fixed It Right The First Time | I9: Showed Me The Old Part | J9: Vendor Team Was Smooth | K9: Taught Our History Right | L9: Culturally Affirming | M9: Hires From The Neighborhood | N9: Felt The Ancestors | O9: Lit My Skin Correctly | P9: Every Kid Plays | Q9: Honest About Treatment Cost | R9: Didn't Talk Down To Me | S9: Explained My Credit Plain | T9: Explained My Rights | U9: Seeds From Home | V9: Alterations Were Perfect
A10: They Don't Rush The Recipe | B10: Edges Respected | C10: Culturally Competent Care | D10: Owner Remembers Me | E10: Real Local Recommendations | F10: Artists Paid Fairly | G10: Fought For Me | H10: Respected My Home | I10: Safe For Women Coming Alone | J10: Florals Were Fresh | K10: Didn't Give Up On My Child | L10: Safe For My Baby | M10: No Hoops To Jump Through | N10: Community Not Just Congregation | O10: Sound Was Crisp | P10: Safe Space For Girls | Q10: Payment Plan Offered | R10: Handed Over The Passwords | S10: No Predatory Terms | T10: Didn't Take My Money And Ghost | U10: Takes EBT / SNAP | V10: Brought My Shoes Back To Life
A11: Ask For The Special | B11: Style Lasted | C11: Understands My Skin | D11: Shelves Reflect Us | E11: Hair-Friendly Water & Towels | F11: Kids Left Inspired | G11: Saved Me Money | H11: Honest About What I Didn't Need | I11: Loaner Or Ride Home Offered | J11: Cake Tasted As Good As It Looked | K11: Discipline Without Disrespect | L11: Diverse Staff | M11: Youth Are Valued | N11: Leadership Knows Your Name | O11: Didn't Steal My Vision | P11: Beginners Welcome | Q11: Groom Was Exactly Right | R11: Site Actually Loads Fast | S11: Got Me Funded | T11: Payment Plan Offered | U11: Land Back In Our Hands | V11: Came Out At 2AM
A12: Recipe From The Motherland | B12: My Shade Was There | C12: Understands My Hair | D12: Wrapped With Care | E12: Breakfast Hit | F12: Free Day Is Real | G12: Took My Small Business Seriously | H12: Warranty Was Real | I12: Detail Was Immaculate | J12: Captured The Real Moments | K12: Financial Aid Help Was Real | L12: My Child Wants To Go Back | M12: Money Reached The People | N12: Youth Are Valued | O12: Paid Their Team | P12: No Ego In Here | Q12: Sent Photos While I Was Gone | R12: Fixed It Same Day | S12: Taught Me To Build Wealth | T12: Handled My Immigration Case With Care | U12: Teaches While Selling | V12: Handled Our Loss With Grace
... A15: Book This Table | B15: Patient With Kids | C15: Therapist Gets The Culture | D15: Take My Money | E15: Driver Was Solid | F15: Got My Angles | G15: Didn't Talk Down To Me | H15: Helped Me Buy My First Home | I15: Driver Was Professional | J15: No Day-Of Drama | K15: Culturally Affirming Curriculum | L15: Never Pushed My Child Out | M15: Advocated At City Hall | N15: Choir Sent Me | O15: Made Me Look Like Me | P15: Discipline With Love | Q15: Save This Vet / Groomer | R15: Hire Them | S15: Free Consult Was Actually Free | T15: Kept My Family Together | U15: Shop Here Before The Cookout | V15: Dry & Secure
A16: Don't Sleep On This One | B16: Book Now | C16: Doula Held Me Down | D16: Don't Leave Without It | E16: Book This Stay | F16: Put This On The Calendar | G16: Hire Them | H16: Actually Fixes Things | I16: Save This Shop | J16: Book Them | K16: Send Your People Here | L16: Parents Put This On The List | M16: Share This Resource | N16: Leader Made Time For Me | O16: Book Them | P16: Taught Me To Swim At Any Age | S16: Send Your People Here | T16: Call Them | V16: Save Their Number
A17: I Sent The Group Chat | B17: Ask For Them By Name | C17: Prices Were Clear Up Front | E17: Add It To The Trip | H17: Save Their Number | N17: Bring Somebody With You | P17: Sign Up
C18: No Judgment About My Body

Sheet THE REAL Reference
A1: Main Category | B1: THE REAL Tag | C1: Type | D1: Subcategory Scope | E1: Helper Text | F1: Origin | G1: Source
A2: Health & Wellness | B2: This Doctor Listens | C2: real-specific | D2: primary care, dental, PT, chiropractic, holistic | E2: They asked, then waited for the whole answer | F2: migrate | G2: Founder PDF p.14
A3: Health & Wellness | B3: Believed My Pain | C3: real-specific | D3: primary care, dental, PT, chiropractic, doula | E3: No minimizing, no doubting, no "are you sure?" | F3: migrate | G3: Founder PDF p.14
A4: Health & Wellness | B4: Believed Me | C4: real-adaptive | D4: all real subcats | E4: They took your account of your own body as true | F4: new | G4: Founder PDF p.14
A5: Health & Wellness | B5: Culturally Competent Care | C5: real-specific | D5: all real subcats | E5: They understand where you come from | F5: migrate | G5: Founder PDF p.14
A6: Health & Wellness | B6: Understands My Skin | C6: real-specific | D6: primary care (dermatology) , wellness centers | E6: Trained on melanated skin, not just textbook photos | F6: migrate | G6: Founder PDF p.14
A7: Health & Wellness | B7: Understands My Hair | C7: real-specific | D7: primary care (dermatology) , wellness centers | E7: Knows textured hair and scalp conditions | F7: migrate | G7: Founder PDF p.14
A8: Health & Wellness | B8: Fought For My Coverage | C8: real-specific | D8: all real subcats | E8: They pushed insurance so you didn't have to | F8: migrate | G8: Founder PDF p.14
A9: Health & Wellness | B9: Knew My Condition Hits Us Different | C9: real-adaptive ( knows_what_ | D9: primary care, dental, PT, chiropractic, holistic, doula | E9: They knew the numbers for our community without being told | F9: new | G9: Founder PDF p.14
A10: Health & Wellness | B10: Didn't Dismiss My Symptoms | C10: real-specific | D10: all real subcats | E10: What you reported was investigated, not filed away | F10: new | G10: Founder PDF p.15
A11: Health & Wellness | B11: Explained Options, Not Just Orders | C11: real-specific | D11: all real subcats | E11: You chose your care, you weren't handed a decision | F11: new | G11: Founder PDF p.15
A12: Health & Wellness | B12: Waited For My Questions | C12: real-specific | D12: all real subcats | E12: Nobody had a hand on the doorknob | F12: new | G12: Founder PDF p.15
... A152: Home & Property Services | B152: Explained First-Time Buyer Programs | C152: real-specific | D152: Real Estate Agents & Brokers; Housing Counselors; Mortgage & Homebuyer Counseling | E152: They showed me assistance and programs I might qualify for | F152: ADDED v2 | G152: Suggested addition

Sheet Layer Routing
A1: Category / Subcategory | B1: Layer | C1: Rule
A2: Food, retail, travel, arts, events, family, faith, recreation and other experience categories | B2: The Vibe | C2: Atmosphere/visit type; What stands out? remains universal
A3: Health & Wellness — clinical/care | B3: THE REAL | C3: Primary care, dental, therapy, PT, chiropractic, nutrition, wellness centers, doula/birth, holistic, pharmacy, home health + v2 clinical specialties
A4: Health & Wellness — Fitness & Gyms / Personal Trainers / Yoga & Pilates | B4: The Vibe | C4: Movement/wellness experience exception
A5: Legal & Government Services | B5: THE REAL | C5: Professional trust
A6: Professional Services | B6: THE REAL | C6: Professional trust
A7: Financial & Business Services | B7: THE REAL | C7: Professional trust
A8: Home & Property Services | B8: THE REAL | C8: Professional/service trust
A9: Automotive & Transportation | B9: THE REAL | C9: Professional/service trust
A10: Technology & Digital Services | B10: THE REAL | C10: Professional/service trust
A11: Pets & Animal Services | B11: THE REAL | C11: Professional/service trust
A12: Other Services | B12: THE REAL | C12: Professional/service trust

Sheet Business Intake v2
A1: Business Name | B1: City | C1: State | D1: Original Category | E1: Main Category | F1: Subcategory | G1: Website or Social Media | H1: Brief Description (1–2 sentences) | I1: Profile Layer | J1: Vibe 1 (if applicable) | K1: Vibe 2 (if applicable) | L1: Vibe 3 (if applicable) | M1: THE REAL 1 (if applicable) | N1: THE REAL 2 (if applicable) | O1: THE REAL 3 (if applicable) | P1: Ownership 1 | Q1: Ownership 2 | R1: Recommended By | S1: Notes | T1: Address | U1: Zip Code | V1: What Stands Out? 1 | W1: What Stands Out? 2 | X1: What Stands Out? 3 | Y1: Verification Status | AA1: HOW THIS INTAKE WORKS
A2: The Nail Jawns | B2: Philadelphia | C2: PA | D2: Nail Salon | E2: Beauty & Personal Care | F2: Nail Salons & Nail Artists | G2: https://www.tiktok.com/@the.nail.jawns | I2: =IFERROR(INDEX('_Layer Lookup v3'!$B$2:$B$267,MATCH($E2&"|"&$F2,'_Layer Lookup v3'!$A$2:$A$267,0)),"") -> The Vibe | P2: Black / African American-Owned | R2: Friend | S2: Walk-ins Welcomed, Appointments preferred. | T2: 429 N. 64th St | U2: 19151 | AA2: 1) Choose Main Category. 2) Choose the matching Subcategory. 3) Profile Layer fills automatically: The Vibe OR THE REAL. 4) Choose up to 3 applicable Vibes or THE REAL trust tags from the dependent dropdowns. 5) Choose up to 3 universal “What Stands Out?” one-tap endorsements. 6) Ownership 1 and 2 remain separate from category, Vibe, THE REAL, and endorsements.
A3: Cherished Beauty Supply | B3: Darby | C3: PA | D3: Beauty | E3: Beauty & Personal Care | F3: Beauty Supply | G3: https://www.tiktok.com/@cherishedbeautysupply | H3: Plant-Based Hair & Skin Care. Black-Owned Beauty Supply | I3: =IFERROR(INDEX('_Layer Lookup v3'!$B$2:$B$267,MATCH($E3&"|"&$F3,'_Layer Lookup v3'!$A$2:$A$267,0)),"") -> The Vibe | P3: Black / African American-Owned | R3: Friend | S3: Willing to Ship! | T3: 526 Main St | U3: 19023
A4: Angie's Eats | B4: Philadelphia | C4: PA | D4: Restaurant | E4: Food & Drink | F4: Restaurants | G4: https://www.tiktok.com/@angieslne | H4: Latin Soul Food | I4: =IFERROR(INDEX('_Layer Lookup v3'!$B$2:$B$267,MATCH($E4&"|"&$F4,'_Layer Lookup v3'!$A$2:$A$267,0)),"") -> The Vibe | P4: Latino / Hispanic-Owned | R4: Personal visit | S4: The Shrimp Alfredo with 6 wings combo is FIRE
A5: ISSAAESTHETICS Beauty Salon & Barbershop | B5: Silver Spring | C5: MD | D5: Barber/Salon | E5: Beauty & Personal Care | F5: Hair Salons | G5: https://www.instagram.com/issaaestheticsbeauty | H5: Laser Hair Removal/Blow Outs/Chemical Peels and More | I5: =IFERROR(INDEX('_Layer Lookup v3'!$B$2:$B$267,MATCH($E5&"|"&$F5,'_Layer Lookup v3'!$A$2:$A$267,0)),"") -> The Vibe | P5: Dominican-Owned | R5: Friend | S5: Se Habla Espanol | T5: 11409 Amherst Ave Unit A | U5: 20902
A6: Candy Clouds By Cass | B6: Santa Clara | C6: CA | D6: Restaurant | E6: Food & Drink | F6: Desserts & Sweets | G6: https://www.instagram.com/candycloudsbycass | H6: Sweet Clouds for Every Celebration! | I6: =IFERROR(INDEX('_Layer Lookup v3'!$B$2:$B$267,MATCH($E6&"|"&$F6,'_Layer Lookup v3'!$A$2:$A$267,0)),"") -> The Vibe | P6: Minority-Owned (general / legacy) | S6: Serving the Bay Area
A7: Little Essentials | B7: New York | C7: NY | E7: Children & Family | F7: Children's Retail | I7: =IFERROR(INDEX('_Layer Lookup v3'!$B$2:$B$267,MATCH($E7&"|"&$F7,'_Layer Lookup v3'!$A$2:$A$267,0)),"") -> The Vibe
I8: =IFERROR(INDEX('_Layer Lookup v3'!$B$2:$B$267,MATCH($E8&"|"&$F8,'_Layer Lookup v3'!$A$2:$A$267,0)),"")
I9: =IFERROR(INDEX('_Layer Lookup v3'!$B$2:$B$267,MATCH($E9&"|"&$F9,'_Layer Lookup v3'!$A$2:$A$267,0)),"")
I10: =IFERROR(INDEX('_Layer Lookup v3'!$B$2:$B$267,MATCH($E10&"|"&$F10,'_Layer Lookup v3'!$A$2:$A$267,0)),"")
I11: =IFERROR(INDEX('_Layer Lookup v3'!$B$2:$B$267,MATCH($E11&"|"&$F11,'_Layer Lookup v3'!$A$2:$A$267,0)),"")
I12: =IFERROR(INDEX('_Layer Lookup v3'!$B$2:$B$267,MATCH($E12&"|"&$F12,'_Layer Lookup v3'!$A$2:$A$267,0)),"")
I13: =IFERROR(INDEX('_Layer Lookup v3'!$B$2:$B$267,MATCH($E13&"|"&$F13,'_Layer Lookup v3'!$A$2:$A$267,0)),"")
I14: =IFERROR(INDEX('_Layer Lookup v3'!$B$2:$B$267,MATCH($E14&"|"&$F14,'_Layer Lookup v3'!$A$2:$A$267,0)),"")
I15: =IFERROR(INDEX('_Layer Lookup v3'!$B$2:$B$267,MATCH($E15&"|"&$F15,'_Layer Lookup v3'!$A$2:$A$267,0)),"")
I16: =IFERROR(INDEX('_Layer Lookup v3'!$B$2:$B$267,MATCH($E16&"|"&$F16,'_Layer Lookup v3'!$A$2:$A$267,0)),"")
I17: =IFERROR(INDEX('_Layer Lookup v3'!$B$2:$B$267,MATCH($E17&"|"&$F17,'_Layer Lookup v3'!$A$2:$A$267,0)),"")
I18: =IFERROR(INDEX('_Layer Lookup v3'!$B$2:$B$267,MATCH($E18&"|"&$F18,'_Layer Lookup v3'!$A$2:$A$267,0)),"")
I19: =IFERROR(INDEX('_Layer Lookup v3'!$B$2:$B$267,MATCH($E19&"|"&$F19,'_Layer Lookup v3'!$A$2:$A$267,0)),"")
... I500: =IFERROR(INDEX('_Layer Lookup v3'!$B$2:$B$267,MATCH($E500&"|"&$F500,'_Layer Lookup v3'!$A$2:$A$267,0)),"")

Sheet _Subcategory Dropdowns v3
A1: Food & Drink | B1: Beauty & Personal Care | C1: Health & Wellness | D1: Shopping & Retail | E1: Travel & Hospitality | F1: Arts, Culture & Entertainment | G1: Professional Services | H1: Home & Property Services | I1: Automotive & Transportation | J1: Events & Celebrations | K1: Education & Learning | L1: Children & Family | M1: Community & Nonprofit | N1: Faith & Spirituality | O1: Media & Creative Services | P1: Sports & Recreation | Q1: Pets & Animal Services | R1: Technology & Digital Services | S1: Financial & Business Services | T1: Legal & Government Services | U1: Agriculture & Specialty Producers | V1: Other Services
A2: Restaurants | B2: Hair Salons | C2: Primary Care & Medical Practices | D2: Clothing & Fashion | E2: Hotels & Resorts | F2: Museums | G2: Accounting & Tax | H2: Real Estate Agents & Brokers | I2: Auto Repair | J2: Event Planning | K2: Childcare & Daycare | L2: Childcare | M2: Nonprofits | N2: Churches | O2: Content Creators | P2: Sports Clubs | Q2: Veterinarians | R2: Software Companies | S2: Banks & Credit Unions | T2: Attorneys & Law Firms | U2: Farms | V2: Laundry & Dry Cleaning
A3: Cafés & Coffee | B3: Barbershops | C3: Dental | D3: Shoes & Accessories | E3: Bed & Breakfasts | F3: Galleries | G3: Legal Services | H3: Property Management | I3: Auto Detailing | J3: Wedding Planning | K3: Preschools | L3: Children's Activities | M3: Community Organizations | N3: Mosques | O3: Influencers / Cultural Ambassadors | P3: Recreational Centers | Q3: Pet Grooming | R3: App Developers | S3: Financial Advisors | T3: Mediation | U3: Farmers Markets | V3: Tailoring & Alterations
A4: Bakeries | B4: Braiders & Natural Hair | C4: Mental Wellness & Therapy | D4: Jewelry | E4: Vacation Rentals | F4: Cultural Centers | G4: Insurance | H4: Contractors | I4: Car Wash | J4: Event Venues | K4: Tutoring | L4: Indoor Play | M4: Foundations | N4: Synagogues | O4: Podcasts | P4: Coaches & Training | Q4: Pet Boarding | R4: Web Developers | S4: Bookkeeping | T4: Notary Services | U4: Urban Farms | V4: Shoe Repair
A5: Desserts & Sweets | B5: Nail Salons & Nail Artists | C5: Physical Therapy | D5: Gifts | E5: Travel Agencies & Advisors | F5: Performing Arts | G5: Financial Services | H5: Construction | I5: Tire Services | J5: Party Rentals | K5: Test Preparation | L5: Camps | M5: Mutual Aid | N5: Temples | O5: Radio | P5: Youth Sports | Q5: Dog Walking & Pet Sitting | R5: IT Support | S5: Tax Preparation | T5: Immigration Services | U5: Specialty Growers | V5: Locksmiths
A6: Food Trucks & Mobile Food | B6: Makeup Artists | C6: Chiropractic | D6: Home Décor | E6: Tour Operators | F6: Theaters | G6: Business Consulting | H6: Electricians | I6: Auto Dealers | J6: Decorators | K6: Colleges & Universities | L6: Family Entertainment | M6: Advocacy Organizations | N6: Spiritual Centers | O6: Publications & Magazines | P6: Golf | Q6: Pet Training | R6: Cybersecurity | S6: Lending & Financing | T6: Legal Document Services | U6: Floriculture | V6: Shipping & Mailing
A7: Catering | B7: Estheticians & Skincare | C7: Nutrition & Dietitians | D7: Furniture | E7: Tour Guides | F7: Music & Live Entertainment | G7: Marketing & Advertising | H7: Plumbing | I7: Auto Body & Collision | J7: Florists | K7: HBCUs | L7: Parenting Services | M7: Youth Organizations | N7: Faith-Based Organizations | O7: Writers & Authors | P7: Swimming | Q7: Pet Daycare | R7: AI & Automation | S7: Mortgage Services | T7: Government Offices | U7: Food Producers | V7: Storage
A8: Bars & Lounges | B8: Spas | C8: Fitness & Gyms | D8: Books & Bookstores | E8: Transportation Services | F8: DJs | G8: Public Relations | H8: HVAC | I8: Towing & Roadside Assistance | J8: Balloon Artists | K8: Trade & Vocational Schools | L8: Children's Parties | M8: Senior Services | N8: Religious Bookstores & Retail | O8: Photography | P8: Martial Arts | Q8: Pet Stores & Supplies | R8: SaaS | S8: Credit Services | T8: Public Services | U8: Beverage Producers | V8: Funeral & Memorial Services
A9: Juice & Smoothies | B9: Massage | C9: Personal Trainers | D9: Art & Collectibles | E9: Luggage & Travel Products | F9: Entertainment Venues | G9: Graphic Design & Branding | H9: Landscaping & Lawn Care | I9: Car Rental | J9: DJs & Entertainment | K9: Professional Training | L9: Youth Programs | M9: Community Centers | N9: Faith-Based Community Services | O9: Videography | P9: Dance & Movement | R9: Digital Products | S9: Business Funding | T9: Immigration Attorneys | U9: Agricultural Products | V9: Personal Concierge
A10: Specialty Foods | B10: Lashes & Brows | C10: Yoga & Pilates | D10: Specialty Retail | E10: Travel Experiences | F10: Nightlife | G10: Web & App Development | H10: Cleaning Services | I10: Chauffeur & Private Driver | J10: Photographers | K10: Music Lessons | L10: Children's Retail | M10: Cultural Organizations | O10: Production Companies | P10: Outdoor Recreation | R10: Technology Consulting | S10: Investment Services | T10: Family Law | V10: Other
A11: Meal Prep | B11: Beauty Supply | C11: Wellness Centers | D11: Children's Retail | F11: Festivals | G11: IT & Technology Services | H11: Interior Design | I11: Transportation Companies | J11: Videographers | K11: Dance Schools | L11: Maternity & Baby Services | M11: Professional Associations | O11: Recording Studios | P11: Adventure Experiences | S11: Small Business Banking | T11: Criminal Defense
A12: Grocery & Markets | B12: Cosmetics & Beauty Brands | C12: Doula & Birth Services | D12: Pet Products | F12: Attractions | G12: Printing | H12: Moving Services | J12: Caterers | K12: Art Classes | M12: Chambers & Business Organizations | O12: Music Production | S12: Community Development Financial Institutions (CDFIs) | T12: Civil Rights
A13: Private Chefs | B13: Mobile Beauty Services | C13: Holistic Wellness | D13: Online Shops | F13: Gaming & Recreation | G13: Translation & Language Services | H13: Handyman Services | J13: Cakes & Desserts | K13: Language Instruction | O13: Creative Studios | S13: SBA & Business Loan Services | T13: Employment Law
C14: Pharmacies | F14: Photography | G14: Staffing & Recruiting | H14: Home Inspection | J14: Invitations & Stationery | K14: Educational Programs | T14: Housing & Tenant Law
C15: Home Health & Caregiving | F15: Videography | G15: Virtual Assistants | H15: Roofing | J15: Photo Booths | T15: Estate Planning & Probate
C16: OB-GYN & Women's Health | G16: Career Coaching | H16: Pest Control | T16: Personal Injury
C17: Pediatrics | G17: Executive Coaching | H17: Housing Counselors | T17: Business Law
C18: Dermatology | G18: Grant Writing | H18: Mortgage & Homebuyer Counseling
C19: Cardiology | G19: Procurement & Government Contracting
C20: Maternal-Fetal Medicine
C21: Midwifery
C22: Fertility & Reproductive Health
C23: Urgent Care
C24: Specialist Physicians

Sheet _Vibe Dropdowns v3
A1: Category|Subcategory | B1: Option 1 | C1: Option 2 | D1: Option 3 | E1: Option 4 | F1: Option 5 | G1: Option 6 | H1: Option 7 | I1: Option 8 | J1: Option 9 | K1: Option 10 | L1: Option 11 | M1: Option 12 | N1: Option 13 | O1: Option 14 | P1: Option 15 | Q1: Option 16 | R1: Option 17 | S1: Option 18 | T1: Option 19 | U1: Option 20 | V1: Option 21 | W1: Option 22 | X1: Option 23 | Y1: Option 24 | Z1: Option 25 | AA1: Option 26 | AB1: Option 27 | AC1: Option 28 | AD1: Option 29 | AE1: Option 30 | AF1: Option 31 | AG1: Option 32 | AH1: Option 33 | AI1: Option 34 | AJ1: Option 35 | AK1: Option 36 | AL1: Option 37 | AM1: Option 38 | AN1: Option 39 | AO1: Option 40 | AP1: Option 41 | AQ1: Option 42 | AR1: Option 43 | AS1: Option 44 | AT1: Option 45 | AU1: Option 46 | AV1: Option 47 | AW1: Option 48 | AX1: Option 49 | AY1: Option 50 | AZ1: Option 51
A2: Food & Drink|Restaurants | B2: Date Night | C2: Hood Classic | D2: Bougie Treat | E2: Family Reunion Energy | F2: Sunday Best | G2: Late Night Vibes | H2: Turn Up | I2: Cookout Approved | J2: Like Home | K2: Auntie Energy | L2: Tía Energy | M2: Abuela Approved Energy | N2: Soft Life | O2: Take Somebody From Out of Town | P2: Locals Know | Q2: Passport Energy
A3: Food & Drink|Cafés & Coffee | B3: Date Night | C3: Hood Classic | D3: Bougie Treat | E3: Family Reunion Energy | F3: Sunday Best | G3: Late Night Vibes | H3: Turn Up | I3: Cookout Approved | J3: Like Home | K3: Auntie Energy | L3: Tía Energy | M3: Abuela Approved Energy | N3: Soft Life | O3: Take Somebody From Out of Town | P3: Locals Know | Q3: Passport Energy
A4: Food & Drink|Bakeries | B4: Date Night | C4: Hood Classic | D4: Bougie Treat | E4: Family Reunion Energy | F4: Sunday Best | G4: Late Night Vibes | H4: Turn Up | I4: Cookout Approved | J4: Like Home | K4: Auntie Energy | L4: Tía Energy | M4: Abuela Approved Energy | N4: Soft Life | O4: Take Somebody From Out of Town | P4: Locals Know | Q4: Passport Energy
A5: Food & Drink|Desserts & Sweets | B5: Date Night | C5: Hood Classic | D5: Bougie Treat | E5: Family Reunion Energy | F5: Sunday Best | G5: Late Night Vibes | H5: Turn Up | I5: Cookout Approved | J5: Like Home | K5: Auntie Energy | L5: Tía Energy | M5: Abuela Approved Energy | N5: Soft Life | O5: Take Somebody From Out of Town | P5: Locals Know | Q5: Passport Energy
A6: Food & Drink|Food Trucks & Mobile Food | B6: Date Night | C6: Hood Classic | D6: Bougie Treat | E6: Family Reunion Energy | F6: Sunday Best | G6: Late Night Vibes | H6: Turn Up | I6: Cookout Approved | J6: Like Home | K6: Auntie Energy | L6: Tía Energy | M6: Abuela Approved Energy | N6: Soft Life | O6: Take Somebody From Out of Town | P6: Locals Know | Q6: Passport Energy
A7: Food & Drink|Catering | B7: Date Night | C7: Hood Classic | D7: Bougie Treat | E7: Family Reunion Energy | F7: Sunday Best | G7: Late Night Vibes | H7: Turn Up | I7: Cookout Approved | J7: Like Home | K7: Auntie Energy | L7: Tía Energy | M7: Abuela Approved Energy | N7: Soft Life | O7: Take Somebody From Out of Town | P7: Locals Know | Q7: Passport Energy
A8: Food & Drink|Bars & Lounges | B8: Date Night | C8: Hood Classic | D8: Bougie Treat | E8: Family Reunion Energy | F8: Sunday Best | G8: Late Night Vibes | H8: Turn Up | I8: Cookout Approved | J8: Like Home | K8: Auntie Energy | L8: Tía Energy | M8: Abuela Approved Energy | N8: Soft Life | O8: Take Somebody From Out of Town | P8: Locals Know | Q8: Passport Energy
A9: Food & Drink|Juice & Smoothies | B9: Date Night | C9: Hood Classic | D9: Bougie Treat | E9: Family Reunion Energy | F9: Sunday Best | G9: Late Night Vibes | H9: Turn Up | I9: Cookout Approved | J9: Like Home | K9: Auntie Energy | L9: Tía Energy | M9: Abuela Approved Energy | N9: Soft Life | O9: Take Somebody From Out of Town | P9: Locals Know | Q9: Passport Energy
A10: Food & Drink|Specialty Foods | B10: Date Night | C10: Hood Classic | D10: Bougie Treat | E10: Family Reunion Energy | F10: Sunday Best | G10: Late Night Vibes | H10: Turn Up | I10: Cookout Approved | J10: Like Home | K10: Auntie Energy | L10: Tía Energy | M10: Abuela Approved Energy | N10: Soft Life | O10: Take Somebody From Out of Town | P10: Locals Know | Q10: Passport Energy
A11: Food & Drink|Meal Prep | B11: Date Night | C11: Hood Classic | D11: Bougie Treat | E11: Family Reunion Energy | F11: Sunday Best | G11: Late Night Vibes | H11: Turn Up | I11: Cookout Approved | J11: Like Home | K11: Auntie Energy | L11: Tía Energy | M11: Abuela Approved Energy | N11: Soft Life | O11: Take Somebody From Out of Town | P11: Locals Know | Q11: Passport Energy
A12: Food & Drink|Grocery & Markets | B12: Date Night | C12: Hood Classic | D12: Bougie Treat | E12: Family Reunion Energy | F12: Sunday Best | G12: Late Night Vibes | H12: Turn Up | I12: Cookout Approved | J12: Like Home | K12: Auntie Energy | L12: Tía Energy | M12: Abuela Approved Energy | N12: Soft Life | O12: Take Somebody From Out of Town | P12: Locals Know | Q12: Passport Energy
A13: Food & Drink|Private Chefs | B13: Date Night | C13: Hood Classic | D13: Bougie Treat | E13: Family Reunion Energy | F13: Sunday Best | G13: Late Night Vibes | H13: Turn Up | I13: Cookout Approved | J13: Like Home | K13: Auntie Energy | L13: Tía Energy | M13: Abuela Approved Energy | N13: Soft Life | O13: Take Somebody From Out of Town | P13: Locals Know | Q13: Passport Energy
A14: Beauty & Personal Care|Hair Salons | B14: Soft Life | C14: Auntie Energy | D14: Tía Energy | E14: Main Character Energy | F14: Sunday Best | G14: Chill & Restore | H14: Come As You Are | I14: For The Culture | J14: Neighborhood Love | K14: Luxury Without The Attitude
A15: Beauty & Personal Care|Barbershops | B15: Soft Life | C15: Auntie Energy | D15: Tía Energy | E15: Main Character Energy | F15: Sunday Best | G15: Chill & Restore | H15: Come As You Are | I15: For The Culture | J15: Neighborhood Love | K15: Luxury Without The Attitude
A16: Beauty & Personal Care|Braiders & Natural Hair | B16: Soft Life | C16: Auntie Energy | D16: Tía Energy | E16: Main Character Energy | F16: Sunday Best | G16: Chill & Restore | H16: Come As You Are | I16: For The Culture | J16: Neighborhood Love | K16: Luxury Without The Attitude
A17: Beauty & Personal Care|Nail Salons & Nail Artists | B17: Soft Life | C17: Auntie Energy | D17: Tía Energy | E17: Main Character Energy | F17: Sunday Best | G17: Chill & Restore | H17: Come As You Are | I17: For The Culture | J17: Neighborhood Love | K17: Luxury Without The Attitude
A18: Beauty & Personal Care|Makeup Artists | B18: Soft Life | C18: Auntie Energy | D18: Tía Energy | E18: Main Character Energy | F18: Sunday Best | G18: Chill & Restore | H18: Come As You Are | I18: For The Culture | J18: Neighborhood Love | K18: Luxury Without The Attitude
A19: Beauty & Personal Care|Estheticians & Skincare | B19: Soft Life | C19: Auntie Energy | D19: Tía Energy | E19: Main Character Energy | F19: Sunday Best | G19: Chill & Restore | H19: Come As You Are | I19: For The Culture | J19: Neighborhood Love | K19: Luxury Without The Attitude
A20: Beauty & Personal Care|Spas | B20: Soft Life | C20: Auntie Energy | D20: Tía Energy | E20: Main Character Energy | F20: Sunday Best | G20: Chill & Restore | H20: Come As You Are | I20: For The Culture | J20: Neighborhood Love | K20: Luxury Without The Attitude
A21: Beauty & Personal Care|Massage | B21: Soft Life | C21: Auntie Energy | D21: Tía Energy | E21: Main Character Energy | F21: Sunday Best | G21: Chill & Restore | H21: Come As You Are | I21: For The Culture | J21: Neighborhood Love | K21: Luxury Without The Attitude
A22: Beauty & Personal Care|Lashes & Brows | B22: Soft Life | C22: Auntie Energy | D22: Tía Energy | E22: Main Character Energy | F22: Sunday Best | G22: Chill & Restore | H22: Come As You Are | I22: For The Culture | J22: Neighborhood Love | K22: Luxury Without The Attitude
A23: Beauty & Personal Care|Beauty Supply | B23: Soft Life | C23: Auntie Energy | D23: Tía Energy | E23: Main Character Energy | F23: Sunday Best | G23: Chill & Restore | H23: Come As You Are | I23: For The Culture | J23: Neighborhood Love | K23: Luxury Without The Attitude
A24: Beauty & Personal Care|Cosmetics & Beauty Brands | B24: Soft Life | C24: Auntie Energy | D24: Tía Energy | E24: Main Character Energy | F24: Sunday Best | G24: Chill & Restore | H24: Come As You Are | I24: For The Culture | J24: Neighborhood Love | K24: Luxury Without The Attitude
A25: Beauty & Personal Care|Mobile Beauty Services | B25: Soft Life | C25: Auntie Energy | D25: Tía Energy | E25: Main Character Energy | F25: Sunday Best | G25: Chill & Restore | H25: Come As You Are | I25: For The Culture | J25: Neighborhood Love | K25: Luxury Without The Attitude
A26: Health & Wellness|Primary Care & Medical Practices | B26: N/A — This profile uses THE REAL
A27: Health & Wellness|Dental | B27: N/A — This profile uses THE REAL
A28: Health & Wellness|Mental Wellness & Therapy | B28: N/A — This profile uses THE REAL
A29: Health & Wellness|Physical Therapy | B29: N/A — This profile uses THE REAL
A30: Health & Wellness|Chiropractic | B30: N/A — This profile uses THE REAL
A31: Health & Wellness|Nutrition & Dietitians | B31: N/A — This profile uses THE REAL
A32: Health & Wellness|Fitness & Gyms | B32: Chill & Restore | C32: Peaceful Energy | D32: Come As You Are | E32: Auntie Energy | F32: Family Care | G32: Wellness Reset
A33: Health & Wellness|Personal Trainers | B33: Chill & Restore | C33: Peaceful Energy | D33: Come As You Are | E33: Auntie Energy | F33: Family Care | G33: Wellness Reset
A34: Health & Wellness|Yoga & Pilates | B34: Chill & Restore | C34: Peaceful Energy | D34: Come As You Are | E34: Auntie Energy | F34: Family Care | G34: Wellness Reset
A35: Health & Wellness|Wellness Centers | B35: N/A — This profile uses THE REAL
A36: Health & Wellness|Doula & Birth Services | B36: N/A — This profile uses THE REAL
A37: Health & Wellness|Holistic Wellness | B37: N/A — This profile uses THE REAL
A38: Health & Wellness|Pharmacies | B38: N/A — This profile uses THE REAL
A39: Health & Wellness|Home Health & Caregiving | B39: N/A — This profile uses THE REAL
A40: Health & Wellness|OB-GYN & Women's Health | B40: N/A — This profile uses THE REAL
A41: Health & Wellness|Pediatrics | B41: N/A — This profile uses THE REAL
A42: Health & Wellness|Dermatology | B42: N/A — This profile uses THE REAL
A43: Health & Wellness|Cardiology | B43: N/A — This profile uses THE REAL
A44: Health & Wellness|Maternal-Fetal Medicine | B44: N/A — This profile uses THE REAL
A45: Health & Wellness|Midwifery | B45: N/A — This profile uses THE REAL
A46: Health & Wellness|Fertility & Reproductive Health | B46: N/A — This profile uses THE REAL
... A48: Health & Wellness|Specialist Physicians | B48: N/A — This profile uses THE REAL
A49: Shopping & Retail|Clothing & Fashion | B49: Hood Classic | C49: Locals Know | D49: Hidden Gem | E49: Bougie Treat | F49: Chill & Create | G49: Bring The Cousins | H49: For The Culture | I49: Take Somebody From Out of Town
A50: Shopping & Retail|Shoes & Accessories | B50: Hood Classic | C50: Locals Know | D50: Hidden Gem | E50: Bougie Treat | F50: Chill & Create | G50: Bring The Cousins | H50: For The Culture | I50: Take Somebody From Out of Town
A51: Shopping & Retail|Jewelry | B51: Hood Classic | C51: Locals Know | D51: Hidden Gem | E51: Bougie Treat | F51: Chill & Create | G51: Bring The Cousins | H51: For The Culture | I51: Take Somebody From Out of Town
A52: Shopping & Retail|Gifts | B52: Hood Classic | C52: Locals Know | D52: Hidden Gem | E52: Bougie Treat | F52: Chill & Create | G52: Bring The Cousins | H52: For The Culture | I52: Take Somebody From Out of Town
A53: Shopping & Retail|Home Décor | B53: Hood Classic | C53: Locals Know | D53: Hidden Gem | E53: Bougie Treat | F53: Chill & Create | G53: Bring The Cousins | H53: For The Culture | I53: Take Somebody From Out of Town
A54: Shopping & Retail|Furniture | B54: Hood Classic | C54: Locals Know | D54: Hidden Gem | E54: Bougie Treat | F54: Chill & Create | G54: Bring The Cousins | H54: For The Culture | I54: Take Somebody From Out of Town
A55: Shopping & Retail|Books & Bookstores | B55: Hood Classic | C55: Locals Know | D55: Hidden Gem | E55: Bougie Treat | F55: Chill & Create | G55: Bring The Cousins | H55: For The Culture | I55: Take Somebody From Out of Town
A56: Shopping & Retail|Art & Collectibles | B56: Hood Classic | C56: Locals Know | D56: Hidden Gem | E56: Bougie Treat | F56: Chill & Create | G56: Bring The Cousins | H56: For The Culture | I56: Take Somebody From Out of Town
A57: Shopping & Retail|Specialty Retail | B57: Hood Classic | C57: Locals Know | D57: Hidden Gem | E57: Bougie Treat | F57: Chill & Create | G57: Bring The Cousins | H57: For The Culture | I57: Take Somebody From Out of Town
A58: Shopping & Retail|Children's Retail | B58: Hood Classic | C58: Locals Know | D58: Hidden Gem | E58: Bougie Treat | F58: Chill & Create | G58: Bring The Cousins | H58: For The Culture | I58: Take Somebody From Out of Town
A59: Shopping & Retail|Pet Products | B59: Hood Classic | C59: Locals Know | D59: Hidden Gem | E59: Bougie Treat | F59: Chill & Create | G59: Bring The Cousins | H59: For The Culture | I59: Take Somebody From Out of Town
A60: Shopping & Retail|Online Shops | B60: Hood Classic | C60: Locals Know | D60: Hidden Gem | E60: Bougie Treat | F60: Chill & Create | G60: Bring The Cousins | H60: For The Culture | I60: Take Somebody From Out of Town
A61: Travel & Hospitality|Hotels & Resorts | B61: Romantic Escape | C61: Family Reunion Energy | D61: Solo Traveler Comfortable | E61: Bougie Treat | F61: Chill & Restore | G61: Girls Trip Ready | H61: Grand Rising | I61: Bring The Cousins | J61: Passport Energy | K61: Take Somebody From Out of Town | L61: Luxury Without The Attitude | M61: Locals Know
A62: Travel & Hospitality|Bed & Breakfasts | B62: Romantic Escape | C62: Family Reunion Energy | D62: Solo Traveler Comfortable | E62: Bougie Treat | F62: Chill & Restore | G62: Girls Trip Ready | H62: Grand Rising | I62: Bring The Cousins | J62: Passport Energy | K62: Take Somebody From Out of Town | L62: Luxury Without The Attitude | M62: Locals Know
A63: Travel & Hospitality|Vacation Rentals | B63: Romantic Escape | C63: Family Reunion Energy | D63: Solo Traveler Comfortable | E63: Bougie Treat | F63: Chill & Restore | G63: Girls Trip Ready | H63: Grand Rising | I63: Bring The Cousins | J63: Passport Energy | K63: Take Somebody From Out of Town | L63: Luxury Without The Attitude | M63: Locals Know
A64: Travel & Hospitality|Travel Agencies & Advisors | B64: Romantic Escape | C64: Family Reunion Energy | D64: Solo Traveler Comfortable | E64: Bougie Treat | F64: Chill & Restore | G64: Girls Trip Ready | H64: Grand Rising | I64: Bring The Cousins | J64: Passport Energy | K64: Take Somebody From Out of Town | L64: Luxury Without The Attitude | M64: Locals Know
A65: Travel & Hospitality|Tour Operators | B65: Romantic Escape | C65: Family Reunion Energy | D65: Solo Traveler Comfortable | E65: Bougie Treat | F65: Chill & Restore | G65: Girls Trip Ready | H65: Grand Rising | I65: Bring The Cousins | J65: Passport Energy | K65: Take Somebody From Out of Town | L65: Luxury Without The Attitude | M65: Locals Know
A66: Travel & Hospitality|Tour Guides | B66: Romantic Escape | C66: Family Reunion Energy | D66: Solo Traveler Comfortable | E66: Bougie Treat | F66: Chill & Restore | G66: Girls Trip Ready | H66: Grand Rising | I66: Bring The Cousins | J66: Passport Energy | K66: Take Somebody From Out of Town | L66: Luxury Without The Attitude | M66: Locals Know
A67: Travel & Hospitality|Transportation Services | B67: Romantic Escape | C67: Family Reunion Energy | D67: Solo Traveler Comfortable | E67: Bougie Treat | F67: Chill & Restore | G67: Girls Trip Ready | H67: Grand Rising | I67: Bring The Cousins | J67: Passport Energy | K67: Take Somebody From Out of Town | L67: Luxury Without The Attitude | M67: Locals Know
A68: Travel & Hospitality|Luggage & Travel Products | B68: Romantic Escape | C68: Family Reunion Energy | D68: Solo Traveler Comfortable | E68: Bougie Treat | F68: Chill & Restore | G68: Girls Trip Ready | H68: Grand Rising | I68: Bring The Cousins | J68: Passport Energy | K68: Take Somebody From Out of Town | L68: Luxury Without The Attitude | M68: Locals Know
A69: Travel & Hospitality|Travel Experiences | B69: Romantic Escape | C69: Family Reunion Energy | D69: Solo Traveler Comfortable | E69: Bougie Treat | F69: Chill & Restore | G69: Girls Trip Ready | H69: Grand Rising | I69: Bring The Cousins | J69: Passport Energy | K69: Take Somebody From Out of Town | L69: Luxury Without The Attitude | M69: Locals Know
A70: Arts, Culture & Entertainment|Museums | B70: Date Night | C70: Turn Up | D70: Grown & Sexy | E70: Hood Classic | F70: Chill & Create | G70: Late Night Vibes | H70: Family Reunion Energy | I70: Sunday Best | J70: History Lives Here | K70: Culture On The Walls | L70: Teach The Kids | M70: Creative Scene
A71: Arts, Culture & Entertainment|Galleries | B71: Date Night | C71: Turn Up | D71: Grown & Sexy | E71: Hood Classic | F71: Chill & Create | G71: Late Night Vibes | H71: Family Reunion Energy | I71: Sunday Best | J71: History Lives Here | K71: Culture On The Walls | L71: Teach The Kids | M71: Creative Scene
A72: Arts, Culture & Entertainment|Cultural Centers | B72: Date Night | C72: Turn Up | D72: Grown & Sexy | E72: Hood Classic | F72: Chill & Create | G72: Late Night Vibes | H72: Family Reunion Energy | I72: Sunday Best | J72: History Lives Here | K72: Culture On The Walls | L72: Teach The Kids | M72: Creative Scene
... A83: Arts, Culture & Entertainment|Videography | B83: Date Night | C83: Turn Up | D83: Grown & Sexy | E83: Hood Classic | F83: Chill & Create | G83: Late Night Vibes | H83: Family Reunion Energy | I83: Sunday Best | J83: History Lives Here | K83: Culture On The Walls | L83: Teach The Kids | M83: Creative Scene
A84: Professional Services|Accounting & Tax | B84: N/A — This profile uses THE REAL
A85: Professional Services|Legal Services | B85: N/A — This profile uses THE REAL
A86: Professional Services|Insurance | B86: N/A — This profile uses THE REAL
A87: Professional Services|Financial Services | B87: N/A — This profile uses THE REAL
A88: Professional Services|Business Consulting | B88: N/A — This profile uses THE REAL
A89: Professional Services|Marketing & Advertising | B89: N/A — This profile uses THE REAL
A90: Professional Services|Public Relations | B90: N/A — This profile uses THE REAL
A91: Professional Services|Graphic Design & Branding | B91: N/A — This profile uses THE REAL
A92: Professional Services|Web & App Development | B92: N/A — This profile uses THE REAL
A93: Professional Services|IT & Technology Services | B93: N/A — This profile uses THE REAL
A94: Professional Services|Printing | B94: N/A — This profile uses THE REAL
A95: Professional Services|Translation & Language Services | B95: N/A — This profile uses THE REAL
... A128: Automotive & Transportation|Transportation Companies | B128: N/A — This profile uses THE REAL
A129: Events & Celebrations|Event Planning | B129: Family Reunion Energy | C129: Sunday Best | D129: Turn Up | E129: Grown & Sexy | F129: Bougie Treat | G129: Kid Chaos Friendly | H129: Late Night Vibes | I129: Cookout Approved | J129: Made For Memories | K129: Bring The Cousins | L129: Luxury Without The Attitude
A130: Events & Celebrations|Wedding Planning | B130: Family Reunion Energy | C130: Sunday Best | D130: Turn Up | E130: Grown & Sexy | F130: Bougie Treat | G130: Kid Chaos Friendly | H130: Late Night Vibes | I130: Cookout Approved | J130: Made For Memories | K130: Bring The Cousins | L130: Luxury Without The Attitude
A131: Events & Celebrations|Event Venues | B131: Family Reunion Energy | C131: Sunday Best | D131: Turn Up | E131: Grown & Sexy | F131: Bougie Treat | G131: Kid Chaos Friendly | H131: Late Night Vibes | I131: Cookout Approved | J131: Made For Memories | K131: Bring The Cousins | L131: Luxury Without The Attitude
A132: Events & Celebrations|Party Rentals | B132: Family Reunion Energy | C132: Sunday Best | D132: Turn Up | E132: Grown & Sexy | F132: Bougie Treat | G132: Kid Chaos Friendly | H132: Late Night Vibes | I132: Cookout Approved | J132: Made For Memories | K132: Bring The Cousins | L132: Luxury Without The Attitude
A133: Events & Celebrations|Decorators | B133: Family Reunion Energy | C133: Sunday Best | D133: Turn Up | E133: Grown & Sexy | F133: Bougie Treat | G133: Kid Chaos Friendly | H133: Late Night Vibes | I133: Cookout Approved | J133: Made For Memories | K133: Bring The Cousins | L133: Luxury Without The Attitude
A134: Events & Celebrations|Florists | B134: Family Reunion Energy | C134: Sunday Best | D134: Turn Up | E134: Grown & Sexy | F134: Bougie Treat | G134: Kid Chaos Friendly | H134: Late Night Vibes | I134: Cookout Approved | J134: Made For Memories | K134: Bring The Cousins | L134: Luxury Without The Attitude
A135: Events & Celebrations|Balloon Artists | B135: Family Reunion Energy | C135: Sunday Best | D135: Turn Up | E135: Grown & Sexy | F135: Bougie Treat | G135: Kid Chaos Friendly | H135: Late Night Vibes | I135: Cookout Approved | J135: Made For Memories | K135: Bring The Cousins | L135: Luxury Without The Attitude
A136: Events & Celebrations|DJs & Entertainment | B136: Family Reunion Energy | C136: Sunday Best | D136: Turn Up | E136: Grown & Sexy | F136: Bougie Treat | G136: Kid Chaos Friendly | H136: Late Night Vibes | I136: Cookout Approved | J136: Made For Memories | K136: Bring The Cousins | L136: Luxury Without The Attitude
A137: Events & Celebrations|Photographers | B137: Family Reunion Energy | C137: Sunday Best | D137: Turn Up | E137: Grown & Sexy | F137: Bougie Treat | G137: Kid Chaos Friendly | H137: Late Night Vibes | I137: Cookout Approved | J137: Made For Memories | K137: Bring The Cousins | L137: Luxury Without The Attitude
A138: Events & Celebrations|Videographers | B138: Family Reunion Energy | C138: Sunday Best | D138: Turn Up | E138: Grown & Sexy | F138: Bougie Treat | G138: Kid Chaos Friendly | H138: Late Night Vibes | I138: Cookout Approved | J138: Made For Memories | K138: Bring The Cousins | L138: Luxury Without The Attitude
A139: Events & Celebrations|Caterers | B139: Family Reunion Energy | C139: Sunday Best | D139: Turn Up | E139: Grown & Sexy | F139: Bougie Treat | G139: Kid Chaos Friendly | H139: Late Night Vibes | I139: Cookout Approved | J139: Made For Memories | K139: Bring The Cousins | L139: Luxury Without The Attitude
A140: Events & Celebrations|Cakes & Desserts | B140: Family Reunion Energy | C140: Sunday Best | D140: Turn Up | E140: Grown & Sexy | F140: Bougie Treat | G140: Kid Chaos Friendly | H140: Late Night Vibes | I140: Cookout Approved | J140: Made For Memories | K140: Bring The Cousins | L140: Luxury Without The Attitude
... A142: Events & Celebrations|Photo Booths | B142: Family Reunion Energy | C142: Sunday Best | D142: Turn Up | E142: Grown & Sexy | F142: Bougie Treat | G142: Kid Chaos Friendly | H142: Late Night Vibes | I142: Cookout Approved | J142: Made For Memories | K142: Bring The Cousins | L142: Luxury Without The Attitude
A143: Education & Learning|Childcare & Daycare | B143: Teach The Kids | C143: Come As You Are | D143: Creative Energy | E143: Community Classroom
A144: Education & Learning|Preschools | B144: Teach The Kids | C144: Come As You Are | D144: Creative Energy | E144: Community Classroom
...

Sheet _THE REAL Dropdowns v3
A1: Category|Subcategory | B1: Option 1 | C1: Option 2 | D1: Option 3 | E1: Option 4 | F1: Option 5 | G1: Option 6 | H1: Option 7 | I1: Option 8 | J1: Option 9 | K1: Option 10 | L1: Option 11 | M1: Option 12 | N1: Option 13 | O1: Option 14 | P1: Option 15 | Q1: Option 16 | R1: Option 17 | S1: Option 18 | T1: Option 19 | U1: Option 20 | V1: Option 21 | W1: Option 22 | X1: Option 23 | Y1: Option 24 | Z1: Option 25 | AA1: Option 26 | AB1: Option 27 | AC1: Option 28 | AD1: Option 29 | AE1: Option 30 | AF1: Option 31 | AG1: Option 32 | AH1: Option 33 | AI1: Option 34 | AJ1: Option 35 | AK1: Option 36 | AL1: Option 37 | AM1: Option 38 | AN1: Option 39 | AO1: Option 40 | AP1: Option 41 | AQ1: Option 42 | AR1: Option 43 | AS1: Option 44 | AT1: Option 45 | AU1: Option 46 | AV1: Option 47 | AW1: Option 48 | AX1: Option 49 | AY1: Option 50 | AZ1: Option 51
A2: Food & Drink|Restaurants | B2: N/A — This profile uses The Vibe
A3: Food & Drink|Cafés & Coffee | B3: N/A — This profile uses The Vibe
A4: Food & Drink|Bakeries | B4: N/A — This profile uses The Vibe
A5: Food & Drink|Desserts & Sweets | B5: N/A — This profile uses The Vibe
A6: Food & Drink|Food Trucks & Mobile Food | B6: N/A — This profile uses The Vibe
A7: Food & Drink|Catering | B7: N/A — This profile uses The Vibe
A8: Food & Drink|Bars & Lounges | B8: N/A — This profile uses The Vibe
A9: Food & Drink|Juice & Smoothies | B9: N/A — This profile uses The Vibe
A10: Food & Drink|Specialty Foods | B10: N/A — This profile uses The Vibe
A11: Food & Drink|Meal Prep | B11: N/A — This profile uses The Vibe
A12: Food & Drink|Grocery & Markets | B12: N/A — This profile uses The Vibe
A13: Food & Drink|Private Chefs | B13: N/A — This profile uses The Vibe
... A25: Beauty & Personal Care|Mobile Beauty Services | B25: N/A — This profile uses The Vibe
A26: Health & Wellness|Primary Care & Medical Practices | B26: This Doctor Listens | C26: Believed My Pain | D26: Believed Me | E26: Culturally Competent Care | F26: Understands My Skin | G26: Understands My Hair | H26: Fought For My Coverage | I26: Knew My Condition Hits Us Different | J26: Didn't Dismiss My Symptoms | K26: Explained Options, Not Just Orders | L26: Waited For My Questions | M26: Remembered My History | N26: Respected My Birth Plan | O26: Advocated When I Couldn't | P26: Gentle With My Child | Q26: Staff Looked Like Me | R26: No Surprise Bills | S26: Didn't Blame Everything On My Weight | T26: Took My Child's Symptoms Seriously
A27: Health & Wellness|Dental | B27: This Doctor Listens | C27: Believed My Pain | D27: Believed Me | E27: Culturally Competent Care | F27: Fought For My Coverage | G27: Knew My Condition Hits Us Different | H27: Didn't Dismiss My Symptoms | I27: Explained Options, Not Just Orders | J27: Waited For My Questions | K27: Remembered My History | L27: Gentle With My Child | M27: Staff Looked Like Me | N27: No Surprise Bills
A28: Health & Wellness|Mental Wellness & Therapy | B28: Believed Me | C28: Culturally Competent Care | D28: Fought For My Coverage | E28: Didn't Dismiss My Symptoms | F28: Explained Options, Not Just Orders | G28: Waited For My Questions | H28: Remembered My History | I28: Advocated When I Couldn't | J28: Therapist Gets The Culture | K28: Staff Looked Like Me | L28: No Surprise Bills
A29: Health & Wellness|Physical Therapy | B29: This Doctor Listens | C29: Believed My Pain | D29: Believed Me | E29: Culturally Competent Care | F29: Fought For My Coverage | G29: Knew My Condition Hits Us Different | H29: Didn't Dismiss My Symptoms | I29: Explained Options, Not Just Orders | J29: Waited For My Questions | K29: Remembered My History | L29: Gentle With My Child | M29: Staff Looked Like Me | N29: No Surprise Bills
A30: Health & Wellness|Chiropractic | B30: This Doctor Listens | C30: Believed My Pain | D30: Believed Me | E30: Culturally Competent Care | F30: Fought For My Coverage | G30: Knew My Condition Hits Us Different | H30: Didn't Dismiss My Symptoms | I30: Explained Options, Not Just Orders | J30: Waited For My Questions | K30: Remembered My History | L30: Staff Looked Like Me | M30: No Surprise Bills
A31: Health & Wellness|Nutrition & Dietitians | B31: Believed Me | C31: Culturally Competent Care | D31: Fought For My Coverage | E31: Didn't Dismiss My Symptoms | F31: Explained Options, Not Just Orders | G31: Waited For My Questions | H31: Staff Looked Like Me | I31: No Surprise Bills
A32: Health & Wellness|Fitness & Gyms | B32: N/A — This profile uses The Vibe
A33: Health & Wellness|Personal Trainers | B33: N/A — This profile uses The Vibe
A34: Health & Wellness|Yoga & Pilates | B34: N/A — This profile uses The Vibe
A35: Health & Wellness|Wellness Centers | B35: Believed Me | C35: Culturally Competent Care | D35: Understands My Skin | E35: Understands My Hair | F35: Fought For My Coverage | G35: Didn't Dismiss My Symptoms | H35: Explained Options, Not Just Orders | I35: Waited For My Questions | J35: Staff Looked Like Me | K35: No Surprise Bills
A36: Health & Wellness|Doula & Birth Services | B36: Believed My Pain | C36: Believed Me | D36: Culturally Competent Care | E36: Fought For My Coverage | F36: Knew My Condition Hits Us Different | G36: Didn't Dismiss My Symptoms | H36: Explained Options, Not Just Orders | I36: Waited For My Questions | J36: Respected My Birth Plan | K36: Advocated When I Couldn't | L36: Doula Held Me Down | M36: Staff Looked Like Me | N36: No Surprise Bills
A37: Health & Wellness|Holistic Wellness | B37: This Doctor Listens | C37: Believed Me | D37: Culturally Competent Care | E37: Fought For My Coverage | F37: Knew My Condition Hits Us Different | G37: Didn't Dismiss My Symptoms | H37: Explained Options, Not Just Orders | I37: Waited For My Questions | J37: Staff Looked Like Me | K37: No Surprise Bills
A38: Health & Wellness|Pharmacies | B38: Believed Me | C38: Culturally Competent Care | D38: Fought For My Coverage | E38: Didn't Dismiss My Symptoms | F38: Explained Options, Not Just Orders | G38: Waited For My Questions | H38: Staff Looked Like Me | I38: No Surprise Bills
A39: Health & Wellness|Home Health & Caregiving | B39: Believed Me | C39: Culturally Competent Care | D39: Fought For My Coverage | E39: Didn't Dismiss My Symptoms | F39: Explained Options, Not Just Orders | G39: Waited For My Questions | H39: Remembered My History | I39: Advocated When I Couldn't | J39: Gentle With My Child | K39: Staff Looked Like Me | L39: No Surprise Bills
A40: Health & Wellness|OB-GYN & Women's Health | B40: This Doctor Listens | C40: Believed My Pain | D40: Believed Me | E40: Culturally Competent Care | F40: Understands My Skin | G40: Understands My Hair | H40: Fought For My Coverage | I40: Knew My Condition Hits Us Different | J40: Didn't Dismiss My Symptoms | K40: Explained Options, Not Just Orders | L40: Waited For My Questions | M40: Remembered My History | N40: Respected My Birth Plan | O40: Advocated When I Couldn't | P40: Gentle With My Child | Q40: Staff Looked Like Me | R40: No Surprise Bills | S40: Explained Every Option | T40: Didn't Blame Everything On My Weight | U40: Took My Reproductive Choices Seriously | V40: Didn't Assume I Wanted Children | W40: Took My Child's Symptoms Seriously
A41: Health & Wellness|Pediatrics | B41: This Doctor Listens | C41: Believed My Pain | D41: Believed Me | E41: Culturally Competent Care | F41: Understands My Skin | G41: Understands My Hair | H41: Fought For My Coverage | I41: Knew My Condition Hits Us Different | J41: Didn't Dismiss My Symptoms | K41: Explained Options, Not Just Orders | L41: Waited For My Questions | M41: Remembered My History | N41: Respected My Birth Plan | O41: Advocated When I Couldn't | P41: Gentle With My Child | Q41: Staff Looked Like Me | R41: No Surprise Bills | S41: Didn't Blame Everything On My Weight | T41: Took My Child's Symptoms Seriously
A42: Health & Wellness|Dermatology | B42: This Doctor Listens | C42: Believed My Pain | D42: Believed Me | E42: Culturally Competent Care | F42: Understands My Skin | G42: Understands My Hair | H42: Fought For My Coverage | I42: Knew My Condition Hits Us Different | J42: Didn't Dismiss My Symptoms | K42: Explained Options, Not Just Orders | L42: Waited For My Questions | M42: Remembered My History | N42: Respected My Birth Plan | O42: Advocated When I Couldn't | P42: Gentle With My Child | Q42: Staff Looked Like Me | R42: No Surprise Bills | S42: Didn't Blame Everything On My Weight | T42: Took My Child's Symptoms Seriously | U42: Understood Melanated Skin
A43: Health & Wellness|Cardiology | B43: This Doctor Listens | C43: Believed My Pain | D43: Believed Me | E43: Culturally Competent Care | F43: Understands My Skin | G43: Understands My Hair | H43: Fought For My Coverage | I43: Knew My Condition Hits Us Different | J43: Didn't Dismiss My Symptoms | K43: Explained Options, Not Just Orders | L43: Waited For My Questions | M43: Remembered My History | N43: Respected My Birth Plan | O43: Advocated When I Couldn't | P43: Gentle With My Child | Q43: Staff Looked Like Me | R43: No Surprise Bills | S43: Didn't Blame Everything On My Weight | T43: Took My Child's Symptoms Seriously | U43: Understood Melanated Skin
A44: Health & Wellness|Maternal-Fetal Medicine | B44: This Doctor Listens | C44: Believed My Pain | D44: Believed Me | E44: Culturally Competent Care | F44: Understands My Skin | G44: Understands My Hair | H44: Fought For My Coverage | I44: Knew My Condition Hits Us Different | J44: Didn't Dismiss My Symptoms | K44: Explained Options, Not Just Orders | L44: Waited For My Questions | M44: Remembered My History | N44: Respected My Birth Plan | O44: Advocated When I Couldn't | P44: Doula Held Me Down | Q44: Gentle With My Child | R44: Staff Looked Like Me | S44: No Surprise Bills | T44: Explained Every Option | U44: Didn't Blame Everything On My Weight | V44: Took My Child's Symptoms Seriously
A45: Health & Wellness|Midwifery | B45: Believed Me | C45: Culturally Competent Care | D45: Fought For My Coverage | E45: Didn't Dismiss My Symptoms | F45: Explained Options, Not Just Orders | G45: Waited For My Questions | H45: Respected My Birth Plan | I45: Advocated When I Couldn't | J45: Doula Held Me Down | K45: Staff Looked Like Me | L45: No Surprise Bills
A46: Health & Wellness|Fertility & Reproductive Health | B46: Believed Me | C46: Culturally Competent Care | D46: Fought For My Coverage | E46: Didn't Dismiss My Symptoms | F46: Explained Options, Not Just Orders | G46: Waited For My Questions | H46: Staff Looked Like Me | I46: No Surprise Bills | J46: Explained Every Option | K46: Didn't Blame Everything On My Weight | L46: Took My Reproductive Choices Seriously | M46: Didn't Assume I Wanted Children
A47: Health & Wellness|Urgent Care | B47: This Doctor Listens | C47: Believed My Pain | D47: Believed Me | E47: Culturally Competent Care | F47: Understands My Skin | G47: Understands My Hair | H47: Fought For My Coverage | I47: Knew My Condition Hits Us Different | J47: Didn't Dismiss My Symptoms | K47: Explained Options, Not Just Orders | L47: Waited For My Questions | M47: Remembered My History | N47: Respected My Birth Plan | O47: Advocated When I Couldn't | P47: Gentle With My Child | Q47: Staff Looked Like Me | R47: No Surprise Bills | S47: Didn't Blame Everything On My Weight | T47: Took My Child's Symptoms Seriously
A48: Health & Wellness|Specialist Physicians | B48: This Doctor Listens | C48: Believed My Pain | D48: Believed Me | E48: Culturally Competent Care | F48: Understands My Skin | G48: Understands My Hair | H48: Fought For My Coverage | I48: Knew My Condition Hits Us Different | J48: Didn't Dismiss My Symptoms | K48: Explained Options, Not Just Orders | L48: Waited For My Questions | M48: Remembered My History | N48: Respected My Birth Plan | O48: Advocated When I Couldn't | P48: Gentle With My Child | Q48: Staff Looked Like Me | R48: No Surprise Bills | S48: Didn't Blame Everything On My Weight | T48: Took My Child's Symptoms Seriously | U48: Understood Melanated Skin
A49: Shopping & Retail|Clothing & Fashion | B49: N/A — This profile uses The Vibe
A50: Shopping & Retail|Shoes & Accessories | B50: N/A — This profile uses The Vibe
A51: Shopping & Retail|Jewelry | B51: N/A — This profile uses The Vibe
A52: Shopping & Retail|Gifts | B52: N/A — This profile uses The Vibe
A53: Shopping & Retail|Home Décor | B53: N/A — This profile uses The Vibe
A54: Shopping & Retail|Furniture | B54: N/A — This profile uses The Vibe
A55: Shopping & Retail|Books & Bookstores | B55: N/A — This profile uses The Vibe
A56: Shopping & Retail|Art & Collectibles | B56: N/A — This profile uses The Vibe
A57: Shopping & Retail|Specialty Retail | B57: N/A — This profile uses The Vibe
A58: Shopping & Retail|Children's Retail | B58: N/A — This profile uses The Vibe
A59: Shopping & Retail|Pet Products | B59: N/A — This profile uses The Vibe
A60: Shopping & Retail|Online Shops | B60: N/A — This profile uses The Vibe
... A83: Arts, Culture & Entertainment|Videography | B83: N/A — This profile uses The Vibe
A84: Professional Services|Accounting & Tax | B84: Fought For Me | C84: Took My Small Business Seriously | D84: Didn't Talk Down To Me | E84: Made My Business Feel Big | F84: Didn't Nickel And Dime Me | G84: Available When I Panicked | H84: Grew With Me | I84: Referred Me To Their People | J84: Kept My Books Clean | K84: Tax Refund Was Right | L84: Explained It Like I Was Smart | M84: Contract Had No Traps | N84: Explained Everything Clearly
A85: Professional Services|Legal Services | B85: Fought For Me | C85: Took My Small Business Seriously | D85: Didn't Talk Down To Me | E85: Made My Business Feel Big | F85: Didn't Nickel And Dime Me | G85: Available When I Panicked | H85: Grew With Me | I85: Referred Me To Their People | J85: Explained It Like I Was Smart | K85: Contract Had No Traps | L85: Explained Everything Clearly
A86: Professional Services|Insurance | B86: Fought For Me | C86: Took My Small Business Seriously | D86: Didn't Talk Down To Me | E86: Made My Business Feel Big | F86: Didn't Nickel And Dime Me | G86: Available When I Panicked | H86: Grew With Me | I86: Referred Me To Their People | J86: Explained It Like I Was Smart | K86: Contract Had No Traps | L86: Explained Everything Clearly
A87: Professional Services|Financial Services | B87: Took My Small Business Seriously | C87: Didn't Talk Down To Me | D87: Made My Business Feel Big | E87: Didn't Nickel And Dime Me | F87: Grew With Me | G87: Referred Me To Their People | H87: Kept My Books Clean | I87: Explained It Like I Was Smart | J87: Contract Had No Traps | K87: Explained Everything Clearly
A88: Professional Services|Business Consulting | B88: Took My Small Business Seriously | C88: Taught Me While They Worked | D88: Didn't Talk Down To Me | E88: Made My Business Feel Big | F88: Understood My Community | G88: Didn't Nickel And Dime Me | H88: Available When I Panicked | I88: Grew With Me | J88: Referred Me To Their People | K88: Explained It Like I Was Smart | L88: Contract Had No Traps | M88: Believed My Vision | N88: Explained Everything Clearly | O88: Didn't Make Me Prove I Belonged In The Room
A89: Professional Services|Marketing & Advertising | B89: Took My Small Business Seriously | C89: Taught Me While They Worked | D89: Didn't Talk Down To Me | E89: Made My Business Feel Big | F89: Understood My Community | G89: Didn't Nickel And Dime Me | H89: Grew With Me | I89: Referred Me To Their People | J89: Explained It Like I Was Smart | K89: Contract Had No Traps | L89: Believed My Vision | M89: Explained Everything Clearly | N89: Didn't Make Me Prove I Belonged In The Room
A90: Professional Services|Public Relations | B90: Took My Small Business Seriously | C90: Didn't Talk Down To Me | D90: Made My Business Feel Big | E90: Understood My Community | F90: Didn't Nickel And Dime Me | G90: Grew With Me | H90: Referred Me To Their People | I90: Explained It Like I Was Smart | J90: Contract Had No Traps | K90: Believed My Vision | L90: Explained Everything Clearly | M90: Didn't Make Me Prove I Belonged In The Room
A91: Professional Services|Graphic Design & Branding | B91: Took My Small Business Seriously | C91: Taught Me While They Worked | D91: Didn't Talk Down To Me | E91: Made My Business Feel Big | F91: Understood My Community | G91: Didn't Nickel And Dime Me | H91: Grew With Me | I91: Referred Me To Their People | J91: Explained It Like I Was Smart | K91: Contract Had No Traps | L91: Believed My Vision | M91: Explained Everything Clearly
A92: Professional Services|Web & App Development | B92: Took My Small Business Seriously | C92: Didn't Talk Down To Me | D92: Made My Business Feel Big | E92: Didn't Nickel And Dime Me | F92: Grew With Me | G92: Referred Me To Their People | H92: Explained It Like I Was Smart | I92: Contract Had No Traps | J92: Explained Everything Clearly
A93: Professional Services|IT & Technology Services | B93: Took My Small Business Seriously | C93: Taught Me While They Worked | D93: Didn't Talk Down To Me | E93: Made My Business Feel Big | F93: Didn't Nickel And Dime Me | G93: Available When I Panicked | H93: Grew With Me | I93: Referred Me To Their People | J93: Explained It Like I Was Smart | K93: Contract Had No Traps | L93: Explained Everything Clearly | M93: Didn't Make Me Prove I Belonged In The Room
A94: Professional Services|Printing | B94: Took My Small Business Seriously | C94: Didn't Talk Down To Me | D94: Made My Business Feel Big | E94: Didn't Nickel And Dime Me | F94: Grew With Me | G94: Referred Me To Their People | H94: Explained It Like I Was Smart | I94: Contract Had No Traps | J94: Explained Everything Clearly
A95: Professional Services|Translation & Language Services | B95: Took My Small Business Seriously | C95: Didn't Talk Down To Me | D95: Made My Business Feel Big | E95: Understood My Community | F95: Didn't Nickel And Dime Me | G95: Grew With Me | H95: Referred Me To Their People | I95: Explained It Like I Was Smart | J95: Contract Had No Traps | K95: Explained Everything Clearly
A96: Professional Services|Staffing & Recruiting | B96: Fought For Me | C96: Took My Small Business Seriously | D96: Didn't Talk Down To Me | E96: Made My Business Feel Big | F96: Understood My Community | G96: Didn't Nickel And Dime Me | H96: Grew With Me | I96: Referred Me To Their People | J96: Explained It Like I Was Smart | K96: Contract Had No Traps | L96: Explained Everything Clearly | M96: Didn't Make Me Prove I Belonged In The Room
A97: Professional Services|Virtual Assistants | B97: Took My Small Business Seriously | C97: Didn't Talk Down To Me | D97: Made My Business Feel Big | E97: Didn't Nickel And Dime Me | F97: Available When I Panicked | G97: Grew With Me | H97: Referred Me To Their People | I97: Explained It Like I Was Smart | J97: Contract Had No Traps | K97: Explained Everything Clearly
A98: Professional Services|Career Coaching | B98: Fought For Me | C98: Took My Small Business Seriously | D98: Didn't Talk Down To Me | E98: Made My Business Feel Big | F98: Understood My Community | G98: Didn't Nickel And Dime Me | H98: Grew With Me | I98: Referred Me To Their People | J98: Explained It Like I Was Smart | K98: Contract Had No Traps | L98: Explained Everything Clearly | M98: Didn't Make Me Prove I Belonged In The Room
A99: Professional Services|Executive Coaching | B99: Took My Small Business Seriously | C99: Taught Me While They Worked | D99: Didn't Talk Down To Me | E99: Made My Business Feel Big | F99: Understood My Community | G99: Didn't Nickel And Dime Me | H99: Available When I Panicked | I99: Grew With Me | J99: Referred Me To Their People | K99: Explained It Like I Was Smart | L99: Contract Had No Traps | M99: Believed My Vision | N99: Explained Everything Clearly | O99: Didn't Make Me Prove I Belonged In The Room
A100: Professional Services|Grant Writing | B100: Took My Small Business Seriously | C100: Taught Me While They Worked | D100: Didn't Talk Down To Me | E100: Made My Business Feel Big | F100: Understood My Community | G100: Didn't Nickel And Dime Me | H100: Available When I Panicked | I100: Grew With Me | J100: Referred Me To Their People | K100: Explained It Like I Was Smart | L100: Contract Had No Traps | M100: Believed My Vision | N100: Explained Everything Clearly | O100: Didn't Make Me Prove I Belonged In The Room
A101: Professional Services|Procurement & Government Contracting | B101: Took My Small Business Seriously | C101: Taught Me While They Worked | D101: Didn't Talk Down To Me | E101: Made My Business Feel Big | F101: Understood My Community | G101: Didn't Nickel And Dime Me | H101: Available When I Panicked | I101: Grew With Me | J101: Referred Me To Their People | K101: Explained It Like I Was Smart | L101: Contract Had No Traps | M101: Believed My Vision | N101: Explained Everything Clearly | O101: Didn't Make Me Prove I Belonged In The Room
A102: Home & Property Services|Real Estate Agents & Brokers | B102: Respected My Home | C102: Didn't Talk Down To Me | D102: Didn't Overcharge For My Zip Code | E102: Showed Up In My Neighborhood | F102: Left My Floors Clean | G102: Good With My Grandmother | H102: Knows What We Face With Housing | I102: Explained It Like I Was Smart | J102: Didn't Steer Me Away From A Neighborhood | K102: Explained First-Time Buyer Programs
A103: Home & Property Services|Property Management | B103: Respected My Home | C103: Didn't Talk Down To Me | D103: Didn't Overcharge For My Zip Code | E103: Showed Up In My Neighborhood | F103: Treated My Apartment Like A House | G103: Left My Floors Clean | H103: Good With My Grandmother | I103: Quote Had No Traps | J103: Knows What We Face With Housing | K103: Explained It Like I Was Smart
A104: Home & Property Services|Contractors | B104: Fixed It Right The First Time | C104: Respected My Home | D104: Honest About What I Didn't Need | E104: Didn't Talk Down To Me | F104: Didn't Overcharge For My Zip Code | G104: Showed Up In My Neighborhood | H104: Treated My Apartment Like A House | I104: Didn't Scare Me Into More Work | J104: Left My Floors Clean | K104: Good With My Grandmother | L104: Quote Had No Traps | M104: Explained It Like I Was Smart
A105: Home & Property Services|Construction | B105: Respected My Home | C105: Didn't Talk Down To Me | D105: Didn't Overcharge For My Zip Code | E105: Showed Up In My Neighborhood | F105: Left My Floors Clean | G105: Good With My Grandmother | H105: Quote Had No Traps | I105: Explained It Like I Was Smart
A106: Home & Property Services|Electricians | B106: Fixed It Right The First Time | C106: Respected My Home | D106: Honest About What I Didn't Need | E106: Didn't Talk Down To Me | F106: Didn't Overcharge For My Zip Code | G106: Showed Up In My Neighborhood | H106: Treated My Apartment Like A House | I106: Didn't Scare Me Into More Work | J106: Left My Floors Clean | K106: Good With My Grandmother | L106: Believed Me About The Problem | M106: Explained It Like I Was Smart
A107: Home & Property Services|Plumbing | B107: Fixed It Right The First Time | C107: Respected My Home | D107: Honest About What I Didn't Need | E107: Didn't Talk Down To Me | F107: Didn't Overcharge For My Zip Code | G107: Showed Up In My Neighborhood | H107: Treated My Apartment Like A House | I107: Didn't Scare Me Into More Work | J107: Left My Floors Clean | K107: Good With My Grandmother | L107: Believed Me About The Problem | M107: Explained It Like I Was Smart
A108: Home & Property Services|HVAC | B108: Fixed It Right The First Time | C108: Respected My Home | D108: Honest About What I Didn't Need | E108: Didn't Talk Down To Me | F108: Didn't Overcharge For My Zip Code | G108: Showed Up In My Neighborhood | H108: Treated My Apartment Like A House | I108: Didn't Scare Me Into More Work | J108: Left My Floors Clean | K108: Good With My Grandmother | L108: Quote Had No Traps | M108: Believed Me About The Problem | N108: Explained It Like I Was Smart
A109: Home & Property Services|Landscaping & Lawn Care | B109: Respected My Home | C109: Didn't Talk Down To Me | D109: Didn't Overcharge For My Zip Code | E109: Showed Up In My Neighborhood | F109: Left My Floors Clean | G109: Good With My Grandmother | H109: Explained It Like I Was Smart
A110: Home & Property Services|Cleaning Services | B110: Respected My Home | C110: Didn't Talk Down To Me | D110: Didn't Overcharge For My Zip Code | E110: Showed Up In My Neighborhood | F110: Treated My Apartment Like A House | G110: Left My Floors Clean | H110: Good With My Grandmother | I110: Explained It Like I Was Smart
A111: Home & Property Services|Interior Design | B111: Respected My Home | C111: Didn't Talk Down To Me | D111: Didn't Overcharge For My Zip Code | E111: Showed Up In My Neighborhood | F111: Left My Floors Clean | G111: Good With My Grandmother | H111: Explained It Like I Was Smart
A112: Home & Property Services|Moving Services | B112: Respected My Home | C112: Didn't Talk Down To Me | D112: Didn't Overcharge For My Zip Code | E112: Showed Up In My Neighborhood | F112: Left My Floors Clean | G112: Good With My Grandmother | H112: Quote Had No Traps | I112: Explained It Like I Was Smart
A113: Home & Property Services|Handyman Services | B113: Fixed It Right The First Time | C113: Respected My Home | D113: Didn't Talk Down To Me | E113: Didn't Overcharge For My Zip Code | F113: Showed Up In My Neighborhood | G113: Treated My Apartment Like A House | H113: Left My Floors Clean | I113: Good With My Grandmother | J113: Explained It Like I Was Smart
A114: Home & Property Services|Home Inspection | B114: Respected My Home | C114: Honest About What I Didn't Need | D114: Didn't Talk Down To Me | E114: Didn't Overcharge For My Zip Code | F114: Showed Up In My Neighborhood | G114: Didn't Scare Me Into More Work | H114: Left My Floors Clean | I114: Good With My Grandmother | J114: Knows What We Face With Housing | K114: Explained It Like I Was Smart
A115: Home & Property Services|Roofing | B115: Fixed It Right The First Time | C115: Respected My Home | D115: Honest About What I Didn't Need | E115: Didn't Talk Down To Me | F115: Didn't Overcharge For My Zip Code | G115: Showed Up In My Neighborhood | H115: Didn't Scare Me Into More Work | I115: Left My Floors Clean | J115: Good With My Grandmother | K115: Quote Had No Traps | L115: Explained It Like I Was Smart
A116: Home & Property Services|Pest Control | B116: Fixed It Right The First Time | C116: Respected My Home | D116: Honest About What I Didn't Need | E116: Didn't Talk Down To Me | F116: Didn't Overcharge For My Zip Code | G116: Showed Up In My Neighborhood | H116: Treated My Apartment Like A House | I116: Didn't Scare Me Into More Work | J116: Left My Floors Clean | K116: Good With My Grandmother | L116: Explained It Like I Was Smart
A117: Home & Property Services|Housing Counselors | B117: Respected My Home | C117: Didn't Talk Down To Me | D117: Didn't Overcharge For My Zip Code | E117: Showed Up In My Neighborhood | F117: Left My Floors Clean | G117: Good With My Grandmother | H117: Knows What We Face With Housing | I117: Explained It Like I Was Smart | J117: Didn't Steer Me Away From A Neighborhood | K117: Explained First-Time Buyer Programs
A118: Home & Property Services|Mortgage & Homebuyer Counseling | B118: Respected My Home | C118: Didn't Talk Down To Me | D118: Didn't Overcharge For My Zip Code | E118: Showed Up In My Neighborhood | F118: Left My Floors Clean | G118: Good With My Grandmother | H118: Explained It Like I Was Smart | I118: Didn't Steer Me Away From A Neighborhood | J118: Explained First-Time Buyer Programs
A119: Automotive & Transportation|Auto Repair | B119: Didn't Upsell Me | C119: Showed Me The Old Part | D119: Safe For Women Coming Alone | E119: Didn't | F119: Gave Me The Real Price First | G119: Didn't Talk Past Me To My Husband | H119: Remembered My Car's History | I119: Honest About What Could Wait | J119: Believed Me About The Sound | K119: Explained It Like I Was Smart | L119: Fought My Insurance For Me | M119: Didn't Leave Me Stranded
A120: Automotive & Transportation|Auto Detailing | B120: Safe For Women Coming Alone | C120: Gave Me The Real Price First | D120: Remembered My Car's History
A121: Automotive & Transportation|Car Wash | B121: Safe For Women Coming Alone | C121: Gave Me The Real Price First
A122: Automotive & Transportation|Tire Services | B122: Didn't Upsell Me | C122: Showed Me The Old Part | D122: Safe For Women Coming Alone | E122: Didn't | F122: Gave Me The Real Price First | G122: Didn't Talk Past Me To My Husband | H122: Remembered My Car's History | I122: Honest About What Could Wait | J122: Believed Me About The Sound | K122: Explained It Like I Was Smart
A123: Automotive & Transportation|Auto Dealers | B123: Didn't Upsell Me | C123: Safe For Women Coming Alone | D123: Didn't | E123: Gave Me The Real Price First | F123: Didn't Talk Past Me To My Husband | G123: Honest About What Could Wait | H123: Financing Had No Traps | I123: Explained It Like I Was Smart
A124: Automotive & Transportation|Auto Body & Collision | B124: Didn't Upsell Me | C124: Showed Me The Old Part | D124: Safe For Women Coming Alone | E124: Didn't | F124: Gave Me The Real Price First | G124: Didn't Talk Past Me To My Husband | H124: Remembered My Car's History | I124: Honest About What Could Wait | J124: Believed Me About The Sound | K124: Explained It Like I Was Smart | L124: Fought My Insurance For Me
A125: Automotive & Transportation|Towing & Roadside Assistance | B125: Safe For Women Coming Alone | C125: Gave Me The Real Price First | D125: Didn't Talk Past Me To My Husband | E125: Explained It Like I Was Smart | F125: Fought My Insurance For Me | G125: Didn't Leave Me Stranded | H125: Knows What We Face On The Road
A126: Automotive & Transportation|Car Rental | B126: Safe For Women Coming Alone | C126: Gave Me The Real Price First | D126: Didn't Leave Me Stranded
A127: Automotive & Transportation|Chauffeur & Private Driver | B127: Safe For Women Coming Alone | C127: Gave Me The Real Price First | D127: Knows What We Face On The Road
A128: Automotive & Transportation|Transportation Companies | B128: Safe For Women Coming Alone | C128: Gave Me The Real Price First | D128: Financing Had No Traps | E128: Didn't Leave Me Stranded | F128: Knows What We Face On The Road
A129: Events & Celebrations|Event Planning | B129: N/A — This profile uses The Vibe
A130: Events & Celebrations|Wedding Planning | B130: N/A — This profile uses The Vibe
A131: Events & Celebrations|Event Venues | B131: N/A — This profile uses The Vibe
A132: Events & Celebrations|Party Rentals | B132: N/A — This profile uses The Vibe
A133: Events & Celebrations|Decorators | B133: N/A — This profile uses The Vibe
...

Sheet _What Stands Out Dropdowns v3
A1: Category|Subcategory | B1: Option 1 | C1: Option 2 | D1: Option 3 | E1: Option 4 | F1: Option 5 | G1: Option 6 | H1: Option 7 | I1: Option 8 | J1: Option 9 | K1: Option 10 | L1: Option 11 | M1: Option 12 | N1: Option 13 | O1: Option 14 | P1: Option 15 | Q1: Option 16 | R1: Option 17 | S1: Option 18 | T1: Option 19 | U1: Option 20 | V1: Option 21 | W1: Option 22 | X1: Option 23 | Y1: Option 24 | Z1: Option 25 | AA1: Option 26 | AB1: Option 27 | AC1: Option 28 | AD1: Option 29 | AE1: Option 30 | AF1: Option 31 | AG1: Option 32 | AH1: Option 33 | AI1: Option 34 | AJ1: Option 35 | AK1: Option 36 | AL1: Option 37 | AM1: Option 38 | AN1: Option 39 | AO1: Option 40 | AP1: Option 41 | AQ1: Option 42 | AR1: Option 43 | AS1: Option 44 | AT1: Option 45 | AU1: Option 46 | AV1: Option 47 | AW1: Option 48 | AX1: Option 49 | AY1: Option 50 | AZ1: Option 51
A2: Food & Drink|Restaurants | B2: Worth The Drive | C2: Portions With Love | D2: Clean & Cared For | E2: Grandma Approved | F2: Cooks Like Home | G2: They Speak My Language | H2: Seasoned Right | I2: Plate Came Correct | J2: They Don't Rush The Recipe | K2: Ask For The Special | L2: Recipe From The Motherland | M2: Fresh, Not Frozen | N2: Book This Table | O2: Don't Sleep On This One | P2: I Sent The Group Chat
A3: Food & Drink|Cafés & Coffee | B3: Worth The Drive | C3: Portions With Love | D3: Clean & Cared For | E3: Grandma Approved | F3: They Speak My Language | G3: Fresh, Not Frozen | H3: Don't Sleep On This One | I3: I Sent The Group Chat
A4: Food & Drink|Bakeries | B4: Worth The Drive | C4: Portions With Love | D4: Clean & Cared For | E4: Grandma Approved | F4: They Speak My Language | G4: They Don't Rush The Recipe | H4: Recipe From The Motherland | I4: Fresh, Not Frozen | J4: Sweet, Not Too Sweet | K4: Don't Sleep On This One | L4: I Sent The Group Chat
A5: Food & Drink|Desserts & Sweets | B5: Worth The Drive | C5: Portions With Love | D5: Clean & Cared For | E5: Grandma Approved | F5: They Speak My Language | G5: Fresh, Not Frozen | H5: Sweet, Not Too Sweet | I5: Don't Sleep On This One | J5: I Sent The Group Chat
A6: Food & Drink|Food Trucks & Mobile Food | B6: Worth The Drive | C6: Portions With Love | D6: Clean & Cared For | E6: Grandma Approved | F6: They Speak My Language | G6: Seasoned Right | H6: Plate Came Correct | I6: Ask For The Special | J6: Fresh, Not Frozen | K6: Don't Sleep On This One | L6: I Sent The Group Chat
A7: Food & Drink|Catering | B7: Worth The Drive | C7: Portions With Love | D7: Clean & Cared For | E7: Grandma Approved | F7: Cooks Like Home | G7: They Speak My Language | H7: Seasoned Right | I7: Fresh, Not Frozen | J7: Don't Sleep On This One | K7: I Sent The Group Chat
A8: Food & Drink|Bars & Lounges | B8: Worth The Drive | C8: Portions With Love | D8: Clean & Cared For | E8: Grandma Approved | F8: They Speak My Language | G8: Ask For The Special | H8: Fresh, Not Frozen | I8: Don't Sleep On This One | J8: I Sent The Group Chat
A9: Food & Drink|Juice & Smoothies | B9: Worth The Drive | C9: Portions With Love | D9: Clean & Cared For | E9: Grandma Approved | F9: They Speak My Language | G9: Fresh, Not Frozen | H9: Sweet, Not Too Sweet | I9: Don't Sleep On This One | J9: I Sent The Group Chat
A10: Food & Drink|Specialty Foods | B10: Worth The Drive | C10: Portions With Love | D10: Clean & Cared For | E10: Grandma Approved | F10: Cooks Like Home | G10: They Speak My Language | H10: They Don't Rush The Recipe | I10: Recipe From The Motherland | J10: Fresh, Not Frozen | K10: Don't Sleep On This One | L10: I Sent The Group Chat
A11: Food & Drink|Meal Prep | B11: Worth The Drive | C11: Portions With Love | D11: Clean & Cared For | E11: Grandma Approved | F11: Cooks Like Home | G11: They Speak My Language | H11: Seasoned Right | I11: Fresh, Not Frozen | J11: Don't Sleep On This One | K11: I Sent The Group Chat
A12: Food & Drink|Grocery & Markets | B12: Worth The Drive | C12: Portions With Love | D12: Clean & Cared For | E12: Grandma Approved | F12: They Speak My Language | G12: Recipe From The Motherland | H12: Fresh, Not Frozen | I12: Don't Sleep On This One | J12: I Sent The Group Chat
A13: Food & Drink|Private Chefs | B13: Worth The Drive | C13: Portions With Love | D13: Clean & Cared For | E13: Grandma Approved | F13: Cooks Like Home | G13: They Speak My Language | H13: Seasoned Right | I13: Fresh, Not Frozen | J13: Book This Table | K13: Don't Sleep On This One | L13: I Sent The Group Chat
A14: Beauty & Personal Care|Hair Salons | B14: On Time, Every Time | C14: Clean Station | D14: Worth The Price | E14: Blessed Hands | F14: They Know Our Hair | G14: Grandma Approved | H14: Braids Didn't Hurt | I14: Edges Respected | J14: Style Lasted | K14: Didn't Overbook Me | L14: Patient With Kids | M14: Book Now | N14: Ask For Them By Name
A15: Beauty & Personal Care|Barbershops | B15: On Time, Every Time | C15: Clean Station | D15: Worth The Price | E15: Blessed Hands | F15: They Know Our Hair | G15: Grandma Approved | H15: Sharpest Lineup | I15: Didn't Overbook Me | J15: Patient With Kids | K15: Book Now | L15: Ask For Them By Name
A16: Beauty & Personal Care|Braiders & Natural Hair | B16: On Time, Every Time | C16: Clean Station | D16: Worth The Price | E16: Blessed Hands | F16: They Know Our Hair | G16: Grandma Approved | H16: Braids Didn't Hurt | I16: Edges Respected | J16: Style Lasted | K16: Didn't Overbook Me | L16: Patient With Kids | M16: Book Now | N16: Ask For Them By Name
A17: Beauty & Personal Care|Nail Salons & Nail Artists | B17: On Time, Every Time | C17: Clean Station | D17: Worth The Price | E17: Blessed Hands | F17: Grandma Approved | G17: Style Lasted | H17: Didn't Overbook Me | I17: Book Now | J17: Ask For Them By Name
A18: Beauty & Personal Care|Makeup Artists | B18: On Time, Every Time | C18: Clean Station | D18: Worth The Price | E18: Blessed Hands | F18: Grandma Approved | G18: My Shade Was There | H18: Didn't Overbook Me | I18: Book Now | J18: Ask For Them By Name
A19: Beauty & Personal Care|Estheticians & Skincare | B19: On Time, Every Time | C19: Clean Station | D19: Worth The Price | E19: Blessed Hands | F19: Grandma Approved | G19: Skin Cleared Up | H19: Didn't Overbook Me | I19: Book Now | J19: Ask For Them By Name
A20: Beauty & Personal Care|Spas | B20: On Time, Every Time | C20: Clean Station | D20: Worth The Price | E20: Blessed Hands | F20: Grandma Approved | G20: Skin Cleared Up | H20: Didn't Overbook Me | I20: Book Now | J20: Ask For Them By Name
A21: Beauty & Personal Care|Massage | B21: On Time, Every Time | C21: Clean Station | D21: Worth The Price | E21: Blessed Hands | F21: Grandma Approved | G21: Didn't Overbook Me | H21: Book Now | I21: Ask For Them By Name
A22: Beauty & Personal Care|Lashes & Brows | B22: On Time, Every Time | C22: Clean Station | D22: Worth The Price | E22: Blessed Hands | F22: Grandma Approved | G22: Edges Respected | H22: Style Lasted | I22: Didn't Overbook Me | J22: Book Now | K22: Ask For Them By Name
A23: Beauty & Personal Care|Beauty Supply | B23: On Time, Every Time | C23: Clean Station | D23: Worth The Price | E23: Blessed Hands | F23: Grandma Approved | G23: My Shade Was There | H23: Didn't Overbook Me | I23: Ask For Them By Name
A24: Beauty & Personal Care|Cosmetics & Beauty Brands | B24: On Time, Every Time | C24: Clean Station | D24: Worth The Price | E24: Blessed Hands | F24: Grandma Approved | G24: My Shade Was There | H24: Didn't Overbook Me | I24: Ask For Them By Name
A25: Beauty & Personal Care|Mobile Beauty Services | B25: On Time, Every Time | C25: Clean Station | D25: Worth The Price | E25: Blessed Hands | F25: They Know Our Hair | G25: Grandma Approved | H25: Didn't Overbook Me | I25: Book Now | J25: Ask For Them By Name
A26: Health & Wellness|Primary Care & Medical Practices | B26: Didn't Rush Me | C26: Took Time To Explain | D26: Made Me Feel Heard | E26: Treated Me Like Family | F26: They Speak My Language | G26: Grandma Trusts Them | H26: This Doctor Listens | I26: Believed My Pain | J26: Culturally Competent Care | K26: Understands My Skin | L26: Understands My Hair | M26: Fought For My Coverage | N26: Front Desk Was Kind | O26: Prices Were Clear Up Front
A27: Health & Wellness|Dental | B27: Didn't Rush Me | C27: Took Time To Explain | D27: Made Me Feel Heard | E27: Treated Me Like Family | F27: They Speak My Language | G27: Grandma Trusts Them | H27: This Doctor Listens | I27: Believed My Pain | J27: Culturally Competent Care | K27: Fought For My Coverage | L27: Front Desk Was Kind | M27: Prices Were Clear Up Front
A28: Health & Wellness|Mental Wellness & Therapy | B28: Didn't Rush Me | C28: Took Time To Explain | D28: Made Me Feel Heard | E28: Treated Me Like Family | F28: They Speak My Language | G28: Grandma Trusts Them | H28: This Doctor Listens | I28: Believed My Pain | J28: Culturally Competent Care | K28: Fought For My Coverage | L28: Front Desk Was Kind | M28: Therapist Gets The Culture | N28: Prices Were Clear Up Front
A29: Health & Wellness|Physical Therapy | B29: Didn't Rush Me | C29: Took Time To Explain | D29: Made Me Feel Heard | E29: Treated Me Like Family | F29: They Speak My Language | G29: Grandma Trusts Them | H29: This Doctor Listens | I29: Believed My Pain | J29: Culturally Competent Care | K29: Fought For My Coverage | L29: Front Desk Was Kind | M29: Prices Were Clear Up Front
A30: Health & Wellness|Chiropractic | B30: Didn't Rush Me | C30: Took Time To Explain | D30: Made Me Feel Heard | E30: Treated Me Like Family | F30: They Speak My Language | G30: Grandma Trusts Them | H30: This Doctor Listens | I30: Believed My Pain | J30: Culturally Competent Care | K30: Fought For My Coverage | L30: Front Desk Was Kind | M30: Prices Were Clear Up Front
A31: Health & Wellness|Nutrition & Dietitians | B31: Didn't Rush Me | C31: Took Time To Explain | D31: Made Me Feel Heard | E31: Treated Me Like Family | F31: They Speak My Language | G31: Grandma Trusts Them | H31: Culturally Competent Care | I31: Fought For My Coverage | J31: Front Desk Was Kind | K31: Prices Were Clear Up Front | L31: No Judgment About My Body
A32: Health & Wellness|Fitness & Gyms | B32: Didn't Rush Me | C32: Took Time To Explain | D32: Made Me Feel Heard | E32: Treated Me Like Family | F32: They Speak My Language | G32: Grandma Trusts Them | H32: Culturally Competent Care | I32: Fought For My Coverage | J32: Front Desk Was Kind | K32: Prices Were Clear Up Front | L32: No Judgment About My Body
A33: Health & Wellness|Personal Trainers | B33: Didn't Rush Me | C33: Took Time To Explain | D33: Made Me Feel Heard | E33: Treated Me Like Family | F33: They Speak My Language | G33: Grandma Trusts Them | H33: Culturally Competent Care | I33: Fought For My Coverage | J33: Front Desk Was Kind | K33: Prices Were Clear Up Front | L33: No Judgment About My Body
A34: Health & Wellness|Yoga & Pilates | B34: Didn't Rush Me | C34: Took Time To Explain | D34: Made Me Feel Heard | E34: Treated Me Like Family | F34: They Speak My Language | G34: Grandma Trusts Them | H34: Culturally Competent Care | I34: Fought For My Coverage | J34: Front Desk Was Kind | K34: Prices Were Clear Up Front | L34: No Judgment About My Body
A35: Health & Wellness|Wellness Centers | B35: Didn't Rush Me | C35: Took Time To Explain | D35: Made Me Feel Heard | E35: Treated Me Like Family | F35: They Speak My Language | G35: Grandma Trusts Them | H35: Culturally Competent Care | I35: Understands My Skin | J35: Understands My Hair | K35: Fought For My Coverage | L35: Front Desk Was Kind | M35: Prices Were Clear Up Front
A36: Health & Wellness|Doula & Birth Services | B36: Didn't Rush Me | C36: Took Time To Explain | D36: Made Me Feel Heard | E36: Treated Me Like Family | F36: They Speak My Language | G36: Grandma Trusts Them | H36: Believed My Pain | I36: Culturally Competent Care | J36: Fought For My Coverage | K36: Front Desk Was Kind | L36: Doula Held Me Down | M36: Prices Were Clear Up Front
A37: Health & Wellness|Holistic Wellness | B37: Didn't Rush Me | C37: Took Time To Explain | D37: Made Me Feel Heard | E37: Treated Me Like Family | F37: They Speak My Language | G37: Grandma Trusts Them | H37: This Doctor Listens | I37: Culturally Competent Care | J37: Fought For My Coverage | K37: Front Desk Was Kind | L37: Prices Were Clear Up Front
A38: Health & Wellness|Pharmacies | B38: Didn't Rush Me | C38: Took Time To Explain | D38: Made Me Feel Heard | E38: Treated Me Like Family | F38: They Speak My Language | G38: Grandma Trusts Them | H38: Culturally Competent Care | I38: Fought For My Coverage | J38: Front Desk Was Kind | K38: Prices Were Clear Up Front
A39: Health & Wellness|Home Health & Caregiving | B39: Didn't Rush Me | C39: Took Time To Explain | D39: Made Me Feel Heard | E39: Treated Me Like Family | F39: They Speak My Language | G39: Grandma Trusts Them | H39: Culturally Competent Care | I39: Fought For My Coverage | J39: Front Desk Was Kind | K39: Prices Were Clear Up Front
A40: Health & Wellness|OB-GYN & Women's Health | B40: Didn't Rush Me | C40: Took Time To Explain | D40: Made Me Feel Heard | E40: Treated Me Like Family | F40: They Speak My Language | G40: Grandma Trusts Them | H40: This Doctor Listens | I40: Believed My Pain | J40: Culturally Competent Care | K40: Understands My Skin | L40: Understands My Hair | M40: Fought For My Coverage | N40: Front Desk Was Kind | O40: Prices Were Clear Up Front
A41: Health & Wellness|Pediatrics | B41: Didn't Rush Me | C41: Took Time To Explain | D41: Made Me Feel Heard | E41: Treated Me Like Family | F41: They Speak My Language | G41: Grandma Trusts Them | H41: This Doctor Listens | I41: Believed My Pain | J41: Culturally Competent Care | K41: Understands My Skin | L41: Understands My Hair | M41: Fought For My Coverage | N41: Front Desk Was Kind | O41: Prices Were Clear Up Front
A42: Health & Wellness|Dermatology | B42: Didn't Rush Me | C42: Took Time To Explain | D42: Made Me Feel Heard | E42: Treated Me Like Family | F42: They Speak My Language | G42: Grandma Trusts Them | H42: This Doctor Listens | I42: Believed My Pain | J42: Culturally Competent Care | K42: Understands My Skin | L42: Understands My Hair | M42: Fought For My Coverage | N42: Front Desk Was Kind | O42: Prices Were Clear Up Front
A43: Health & Wellness|Cardiology | B43: Didn't Rush Me | C43: Took Time To Explain | D43: Made Me Feel Heard | E43: Treated Me Like Family | F43: They Speak My Language | G43: Grandma Trusts Them | H43: This Doctor Listens | I43: Believed My Pain | J43: Culturally Competent Care | K43: Understands My Skin | L43: Understands My Hair | M43: Fought For My Coverage | N43: Front Desk Was Kind | O43: Prices Were Clear Up Front
A44: Health & Wellness|Maternal-Fetal Medicine | B44: Didn't Rush Me | C44: Took Time To Explain | D44: Made Me Feel Heard | E44: Treated Me Like Family | F44: They Speak My Language | G44: Grandma Trusts Them | H44: This Doctor Listens | I44: Believed My Pain | J44: Culturally Competent Care | K44: Understands My Skin | L44: Understands My Hair | M44: Fought For My Coverage | N44: Front Desk Was Kind | O44: Doula Held Me Down | P44: Prices Were Clear Up Front
A45: Health & Wellness|Midwifery | B45: Didn't Rush Me | C45: Took Time To Explain | D45: Made Me Feel Heard | E45: Treated Me Like Family | F45: They Speak My Language | G45: Grandma Trusts Them | H45: Believed My Pain | I45: Culturally Competent Care | J45: Fought For My Coverage | K45: Front Desk Was Kind | L45: Doula Held Me Down | M45: Prices Were Clear Up Front
A46: Health & Wellness|Fertility & Reproductive Health | B46: Didn't Rush Me | C46: Took Time To Explain | D46: Made Me Feel Heard | E46: Treated Me Like Family | F46: They Speak My Language | G46: Grandma Trusts Them | H46: Culturally Competent Care | I46: Fought For My Coverage | J46: Front Desk Was Kind | K46: Prices Were Clear Up Front
A47: Health & Wellness|Urgent Care | B47: Didn't Rush Me | C47: Took Time To Explain | D47: Made Me Feel Heard | E47: Treated Me Like Family | F47: They Speak My Language | G47: Grandma Trusts Them | H47: This Doctor Listens | I47: Believed My Pain | J47: Culturally Competent Care | K47: Understands My Skin | L47: Understands My Hair | M47: Fought For My Coverage | N47: Front Desk Was Kind | O47: Prices Were Clear Up Front
A48: Health & Wellness|Specialist Physicians | B48: Didn't Rush Me | C48: Took Time To Explain | D48: Made Me Feel Heard | E48: Treated Me Like Family | F48: They Speak My Language | G48: Grandma Trusts Them | H48: This Doctor Listens | I48: Believed My Pain | J48: Culturally Competent Care | K48: Understands My Skin | L48: Understands My Hair | M48: Fought For My Coverage | N48: Front Desk Was Kind | O48: Prices Were Clear Up Front
A49: Shopping & Retail|Clothing & Fashion | B49: Quality Held Up | C49: Fair Prices | D49: No Follow-Around | E49: Grandma Approved | F49: For The Culture | G49: Treated Me Like Family | H49: Found My Size | I49: Found My Shade | J49: Owner Remembers Me | K49: Supports Local Makers | L49: Take My Money | M49: Don't Leave Without It
A50: Shopping & Retail|Shoes & Accessories | B50: Quality Held Up | C50: Fair Prices | D50: No Follow-Around | E50: Grandma Approved | F50: For The Culture | G50: Treated Me Like Family | H50: Found My Size | I50: Owner Remembers Me | J50: Supports Local Makers | K50: Take My Money | L50: Don't Leave Without It
A51: Shopping & Retail|Jewelry | B51: Quality Held Up | C51: Fair Prices | D51: No Follow-Around | E51: Grandma Approved | F51: For The Culture | G51: Treated Me Like Family | H51: Owner Remembers Me | I51: Wrapped With Care | J51: Supports Local Makers | K51: Take My Money | L51: Don't Leave Without It
A52: Shopping & Retail|Gifts | B52: Quality Held Up | C52: Fair Prices | D52: No Follow-Around | E52: Grandma Approved | F52: For The Culture | G52: Treated Me Like Family | H52: Found My Shade | I52: Owner Remembers Me | J52: Shelves Reflect Us | K52: Wrapped With Care | L52: Supports Local Makers | M52: Take My Money | N52: Don't Leave Without It
A53: Shopping & Retail|Home Décor | B53: Quality Held Up | C53: Fair Prices | D53: No Follow-Around | E53: Grandma Approved | F53: For The Culture | G53: Treated Me Like Family | H53: Owner Remembers Me | I53: Shelves Reflect Us | J53: Supports Local Makers | K53: Take My Money | L53: Don't Leave Without It
A54: Shopping & Retail|Furniture | B54: Quality Held Up | C54: Fair Prices | D54: No Follow-Around | E54: Grandma Approved | F54: For The Culture | G54: Treated Me Like Family | H54: Owner Remembers Me | I54: Supports Local Makers | J54: Take My Money | K54: Don't Leave Without It
A55: Shopping & Retail|Books & Bookstores | B55: Quality Held Up | C55: Fair Prices | D55: No Follow-Around | E55: Grandma Approved | F55: For The Culture | G55: Treated Me Like Family | H55: Owner Remembers Me | I55: Shelves Reflect Us | J55: Supports Local Makers | K55: Take My Money | L55: Don't Leave Without It
A56: Shopping & Retail|Art & Collectibles | B56: Quality Held Up | C56: Fair Prices | D56: No Follow-Around | E56: Grandma Approved | F56: For The Culture | G56: Treated Me Like Family | H56: Owner Remembers Me | I56: Shelves Reflect Us | J56: Supports Local Makers | K56: Take My Money | L56: Don't Leave Without It
A57: Shopping & Retail|Specialty Retail | B57: Quality Held Up | C57: Fair Prices | D57: No Follow-Around | E57: Grandma Approved | F57: For The Culture | G57: Treated Me Like Family | H57: Found My Shade | I57: Owner Remembers Me | J57: Supports Local Makers | K57: Take My Money | L57: Don't Leave Without It
A58: Shopping & Retail|Children's Retail | B58: Quality Held Up | C58: Fair Prices | D58: No Follow-Around | E58: Grandma Approved | F58: For The Culture | G58: Treated Me Like Family | H58: Found My Size | I58: Owner Remembers Me | J58: Shelves Reflect Us | K58: Supports Local Makers | L58: Take My Money | M58: Don't Leave Without It
A59: Shopping & Retail|Pet Products | B59: Quality Held Up | C59: Fair Prices | D59: No Follow-Around | E59: Grandma Approved | F59: For The Culture | G59: Treated Me Like Family | H59: Owner Remembers Me | I59: Supports Local Makers | J59: Take My Money | K59: Don't Leave Without It
A60: Shopping & Retail|Online Shops | B60: Quality Held Up | C60: Fair Prices | D60: No Follow-Around | E60: Grandma Approved | F60: For The Culture | G60: Treated Me Like Family | H60: Owner Remembers Me | I60: Wrapped With Care | J60: Supports Local Makers | K60: Shipped Fast & Right | L60: Take My Money | M60: Don't Leave Without It
A61: Travel & Hospitality|Hotels & Resorts | B61: Exactly As Pictured | C61: Spotless | D61: Worth The Stay | E61: Treated Me Like Family | F61: They Speak My Language | G61: Felt Safe The Whole Time | H61: Host Checked On Me | I61: Real Local Recommendations | J61: Hair-Friendly Water & Towels | K61: Breakfast Hit | L61: No Side-Eye At Check-In | M61: Book This Stay | N61: Add It To The Trip
A62: Travel & Hospitality|Bed & Breakfasts | B62: Exactly As Pictured | C62: Spotless | D62: Worth The Stay | E62: Treated Me Like Family | F62: They Speak My Language | G62: Felt Safe The Whole Time | H62: Host Checked On Me | I62: Real Local Recommendations | J62: Hair-Friendly Water & Towels | K62: Breakfast Hit | L62: No Side-Eye At Check-In | M62: Book This Stay | N62: Add It To The Trip
A63: Travel & Hospitality|Vacation Rentals | B63: Exactly As Pictured | C63: Spotless | D63: Worth The Stay | E63: Treated Me Like Family | F63: They Speak My Language | G63: Felt Safe The Whole Time | H63: Host Checked On Me | I63: Hair-Friendly Water & Towels | J63: No Side-Eye At Check-In | K63: Book This Stay | L63: Add It To The Trip
A64: Travel & Hospitality|Travel Agencies & Advisors | B64: Worth The Stay | C64: Treated Me Like Family | D64: They Speak My Language | E64: For The Culture | F64: Felt Safe The Whole Time | G64: Real Local Recommendations | H64: Add It To The Trip
A65: Travel & Hospitality|Tour Operators | B65: Worth The Stay | C65: Treated Me Like Family | D65: They Speak My Language | E65: For The Culture | F65: Felt Safe The Whole Time | G65: Took Us To The Real Places | H65: Add It To The Trip
A66: Travel & Hospitality|Tour Guides | B66: Worth The Stay | C66: Treated Me Like Family | D66: They Speak My Language | E66: For The Culture | F66: Felt Safe The Whole Time | G66: Real Local Recommendations | H66: Took Us To The Real Places | I66: Add It To The Trip
A67: Travel & Hospitality|Transportation Services | B67: Worth The Stay | C67: Treated Me Like Family | D67: They Speak My Language | E67: Felt Safe The Whole Time | F67: Driver Was Solid | G67: Add It To The Trip
A68: Travel & Hospitality|Luggage & Travel Products | B68: Worth The Stay | C68: Treated Me Like Family | D68: They Speak My Language | E68: Felt Safe The Whole Time | F68: Add It To The Trip
A69: Travel & Hospitality|Travel Experiences | B69: Exactly As Pictured | C69: Worth The Stay | D69: Treated Me Like Family | E69: They Speak My Language | F69: For The Culture | G69: Felt Safe The Whole Time | H69: Took Us To The Real Places | I69: Add It To The Trip
A70: Arts, Culture & Entertainment|Museums | B70: Worth The Ticket | C70: Staff Was Welcoming | D70: Bring A Friend | E70: For The Culture | F70: Grandma Approved | G70: Our Story Told Right | H70: Kids Left Inspired | I70: Free Day Is Real | J70: No Bag Check Attitude | K70: Put This On The Calendar
A71: Arts, Culture & Entertainment|Galleries | B71: Worth The Ticket | C71: Staff Was Welcoming | D71: Bring A Friend | E71: For The Culture | F71: Our Story Told Right | G71: Artists Paid Fairly | H71: Kids Left Inspired | I71: Free Day Is Real | J71: Put This On The Calendar
A72: Arts, Culture & Entertainment|Cultural Centers | B72: Worth The Ticket | C72: Staff Was Welcoming | D72: Bring A Friend | E72: For The Culture | F72: Grandma Approved | G72: Our Story Told Right | H72: Kids Left Inspired | I72: Free Day Is Real | J72: Put This On The Calendar
A73: Arts, Culture & Entertainment|Performing Arts | B73: Worth The Ticket | C73: Staff Was Welcoming | D73: Bring A Friend | E73: For The Culture | F73: Grandma Approved | G73: Sunday Best Ready | H73: Our Story Told Right | I73: Sound Was Clean | J73: Put This On The Calendar
A74: Arts, Culture & Entertainment|Theaters | B74: Worth The Ticket | C74: Staff Was Welcoming | D74: Bring A Friend | E74: For The Culture | F74: Grandma Approved | G74: Sunday Best Ready | H74: Our Story Told Right | I74: No Bag Check Attitude | J74: Sound Was Clean | K74: Put This On The Calendar
A75: Arts, Culture & Entertainment|Music & Live Entertainment | B75: Worth The Ticket | C75: Staff Was Welcoming | D75: Bring A Friend | E75: For The Culture | F75: DJ Read The Room | G75: Artists Paid Fairly | H75: Sound Was Clean | I75: Put This On The Calendar
A76: Arts, Culture & Entertainment|DJs | B76: Worth The Ticket | C76: Staff Was Welcoming | D76: Bring A Friend | E76: For The Culture | F76: DJ Read The Room | G76: Put This On The Calendar
A77: Arts, Culture & Entertainment|Entertainment Venues | B77: Worth The Ticket | C77: Staff Was Welcoming | D77: Bring A Friend | E77: For The Culture | F77: Sunday Best Ready | G77: DJ Read The Room | H77: Artists Paid Fairly | I77: No Bag Check Attitude | J77: Sound Was Clean | K77: Put This On The Calendar
A78: Arts, Culture & Entertainment|Nightlife | B78: Worth The Ticket | C78: Staff Was Welcoming | D78: Bring A Friend | E78: For The Culture | F78: Sunday Best Ready | G78: DJ Read The Room | H78: No Bag Check Attitude | I78: Put This On The Calendar
A79: Arts, Culture & Entertainment|Festivals | B79: Worth The Ticket | C79: Staff Was Welcoming | D79: Bring A Friend | E79: For The Culture | F79: Grandma Approved | G79: Artists Paid Fairly | H79: Put This On The Calendar
A80: Arts, Culture & Entertainment|Attractions | B80: Worth The Ticket | C80: Staff Was Welcoming | D80: Bring A Friend | E80: For The Culture | F80: Kids Left Inspired | G80: Free Day Is Real | H80: No Bag Check Attitude | I80: Put This On The Calendar
A81: Arts, Culture & Entertainment|Gaming & Recreation | B81: Worth The Ticket | C81: Staff Was Welcoming | D81: Bring A Friend | E81: For The Culture | F81: Put This On The Calendar
A82: Arts, Culture & Entertainment|Photography | B82: Worth The Ticket | C82: Staff Was Welcoming | D82: Bring A Friend | E82: For The Culture | F82: Got My Angles | G82: Put This On The Calendar
A83: Arts, Culture & Entertainment|Videography | B83: Worth The Ticket | C83: Staff Was Welcoming | D83: Bring A Friend | E83: For The Culture | F83: Got My Angles | G83: Put This On The Calendar
A84: Professional Services|Accounting & Tax | B84: Straight With Me | C84: Delivered On Time | D84: Answered The Phone | E84: Treated Me Like Family | F84: They Speak My Language | G84: For The Culture | H84: Explained It Plain | I84: No Surprise Fees | J84: Fought For Me | K84: Saved Me Money | L84: Took My Small Business Seriously | M84: Kept Me In The Loop | N84: Didn't Talk Down To Me | O84: Hire Them
A85: Professional Services|Legal Services | B85: Straight With Me | C85: Delivered On Time | D85: Answered The Phone | E85: Treated Me Like Family | F85: They Speak My Language | G85: For The Culture | H85: Explained It Plain | I85: No Surprise Fees | J85: Fought For Me | K85: Took My Small Business Seriously | L85: Kept Me In The Loop | M85: Didn't Talk Down To Me | N85: Hire Them
A86: Professional Services|Insurance | B86: Straight With Me | C86: Delivered On Time | D86: Answered The Phone | E86: Treated Me Like Family | F86: They Speak My Language | G86: For The Culture | H86: Explained It Plain | I86: No Surprise Fees | J86: Fought For Me | K86: Saved Me Money | L86: Took My Small Business Seriously | M86: Kept Me In The Loop | N86: Didn't Talk Down To Me | O86: Hire Them
A87: Professional Services|Financial Services | B87: Straight With Me | C87: Delivered On Time | D87: Answered The Phone | E87: Treated Me Like Family | F87: They Speak My Language | G87: For The Culture | H87: Explained It Plain | I87: No Surprise Fees | J87: Saved Me Money | K87: Took My Small Business Seriously | L87: Kept Me In The Loop | M87: Didn't Talk Down To Me | N87: Hire Them
A88: Professional Services|Business Consulting | B88: Straight With Me | C88: Delivered On Time | D88: Answered The Phone | E88: Treated Me Like Family | F88: They Speak My Language | G88: For The Culture | H88: Explained It Plain | I88: No Surprise Fees | J88: Saved Me Money | K88: Took My Small Business Seriously | L88: Taught Me While They Worked | M88: Kept Me In The Loop | N88: Didn't Talk Down To Me | O88: Hire Them
A89: Professional Services|Marketing & Advertising | B89: Straight With Me | C89: Delivered On Time | D89: Answered The Phone | E89: Treated Me Like Family | F89: They Speak My Language | G89: For The Culture | H89: Explained It Plain | I89: No Surprise Fees | J89: Took My Small Business Seriously | K89: Taught Me While They Worked | L89: Kept Me In The Loop | M89: Didn't Talk Down To Me | N89: Hire Them
A90: Professional Services|Public Relations | B90: Straight With Me | C90: Delivered On Time | D90: Answered The Phone | E90: Treated Me Like Family | F90: They Speak My Language | G90: For The Culture | H90: Explained It Plain | I90: No Surprise Fees | J90: Took My Small Business Seriously | K90: Kept Me In The Loop | L90: Didn't Talk Down To Me | M90: Hire Them
A91: Professional Services|Graphic Design & Branding | B91: Straight With Me | C91: Delivered On Time | D91: Answered The Phone | E91: Treated Me Like Family | F91: They Speak My Language | G91: For The Culture | H91: Explained It Plain | I91: No Surprise Fees | J91: Took My Small Business Seriously | K91: Taught Me While They Worked | L91: Kept Me In The Loop | M91: Didn't Talk Down To Me | N91: Hire Them
A92: Professional Services|Web & App Development | B92: Straight With Me | C92: Delivered On Time | D92: Answered The Phone | E92: Treated Me Like Family | F92: They Speak My Language | G92: For The Culture | H92: Explained It Plain | I92: No Surprise Fees | J92: Took My Small Business Seriously | K92: Taught Me While They Worked | L92: Kept Me In The Loop | M92: Didn't Talk Down To Me | N92: Hire Them
A93: Professional Services|IT & Technology Services | B93: Straight With Me | C93: Delivered On Time | D93: Answered The Phone | E93: Treated Me Like Family | F93: They Speak My Language | G93: For The Culture | H93: Explained It Plain | I93: No Surprise Fees | J93: Fought For Me | K93: Took My Small Business Seriously | L93: Taught Me While They Worked | M93: Kept Me In The Loop | N93: Didn't Talk Down To Me | O93: Hire Them
A94: Professional Services|Printing | B94: Straight With Me | C94: Delivered On Time | D94: Answered The Phone | E94: Treated Me Like Family | F94: They Speak My Language | G94: For The Culture | H94: Explained It Plain | I94: No Surprise Fees | J94: Took My Small Business Seriously | K94: Kept Me In The Loop | L94: Didn't Talk Down To Me | M94: Hire Them
A95: Professional Services|Translation & Language Services | B95: Straight With Me | C95: Delivered On Time | D95: Answered The Phone | E95: Treated Me Like Family | F95: They Speak My Language | G95: For The Culture | H95: Explained It Plain | I95: No Surprise Fees | J95: Took My Small Business Seriously | K95: Kept Me In The Loop | L95: Didn't Talk Down To Me | M95: Hire Them
A96: Professional Services|Staffing & Recruiting | B96: Straight With Me | C96: Delivered On Time | D96: Answered The Phone | E96: Treated Me Like Family | F96: They Speak My Language | G96: For The Culture | H96: Explained It Plain | I96: No Surprise Fees | J96: Fought For Me | K96: Took My Small Business Seriously | L96: Kept Me In The Loop | M96: Didn't Talk Down To Me | N96: Hire Them
A97: Professional Services|Virtual Assistants | B97: Straight With Me | C97: Delivered On Time | D97: Answered The Phone | E97: Treated Me Like Family | F97: They Speak My Language | G97: For The Culture | H97: Explained It Plain | I97: No Surprise Fees | J97: Took My Small Business Seriously | K97: Kept Me In The Loop | L97: Didn't Talk Down To Me | M97: Hire Them
A98: Professional Services|Career Coaching | B98: Straight With Me | C98: Delivered On Time | D98: Answered The Phone | E98: Treated Me Like Family | F98: They Speak My Language | G98: For The Culture | H98: Explained It Plain | I98: No Surprise Fees | J98: Fought For Me | K98: Took My Small Business Seriously | L98: Kept Me In The Loop | M98: Didn't Talk Down To Me | N98: Hire Them
A99: Professional Services|Executive Coaching | B99: Straight With Me | C99: Delivered On Time | D99: Answered The Phone | E99: Treated Me Like Family | F99: They Speak My Language | G99: For The Culture | H99: Explained It Plain | I99: No Surprise Fees | J99: Saved Me Money | K99: Took My Small Business Seriously | L99: Taught Me While They Worked | M99: Kept Me In The Loop | N99: Didn't Talk Down To Me | O99: Hire Them
A100: Professional Services|Grant Writing | B100: Straight With Me | C100: Delivered On Time | D100: Answered The Phone | E100: Treated Me Like Family | F100: They Speak My Language | G100: For The Culture | H100: Explained It Plain | I100: No Surprise Fees | J100: Saved Me Money | K100: Took My Small Business Seriously | L100: Taught Me While They Worked | M100: Kept Me In The Loop | N100: Didn't Talk Down To Me | O100: Hire Them
...

Sheet _Layer Lookup v3
A1: Category|Subcategory | B1: Profile Layer
A2: Food & Drink|Restaurants | B2: The Vibe
A3: Food & Drink|Cafés & Coffee | B3: The Vibe
A4: Food & Drink|Bakeries | B4: The Vibe
A5: Food & Drink|Desserts & Sweets | B5: The Vibe
A6: Food & Drink|Food Trucks & Mobile Food | B6: The Vibe
A7: Food & Drink|Catering | B7: The Vibe
A8: Food & Drink|Bars & Lounges | B8: The Vibe
A9: Food & Drink|Juice & Smoothies | B9: The Vibe
A10: Food & Drink|Specialty Foods | B10: The Vibe
A11: Food & Drink|Meal Prep | B11: The Vibe
A12: Food & Drink|Grocery & Markets | B12: The Vibe
... A267: Other Services|Other | B267: THE REAL
